{"rows":122,"columns":["user_id","cancel_rate","zero_fill_cancel_rate","cancel_to_order_ratio","avg_fill_ratio","min_fill_ratio","avg_time_to_cancel","min_time_to_cancel","std_time_to_cancel","limit_order_ratio","market_order_ratio","self_trade_count","both_sides_manip","avg_engine_latency","max_engine_latency","unique_sides","unique_instruments","order_book_imbalance","cancel_timing_regularity","avg_price_deviation","quote_to_trade_ratio","latency_cancel_interaction","cancel_intensity_ratio","fill_cancel_interaction","trader_type","predicted_trader_type"],"predictions":[{"user_id":2,"cancel_rate":0.0,"zero_fill_cancel_rate":0.0,"cancel_to_order_ratio":0.0,"avg_fill_ratio":1.0,"min_fill_ratio":1.0,"avg_time_to_cancel":-1773385.3517004445,"min_time_to_cancel":-1773385.35170164,"std_time_to_cancel":1.6908130242456317e-06,"limit_order_ratio":0.0,"market_order_ratio":0.0,"self_trade_count":0,"both_sides_manip":0,"avg_engine_latency":1.5000000000000002e-08,"max_engine_latency":1.6e-08,"unique_sides":1,"unique_instruments":1,"order_book_imbalance":1.0,"cancel_timing_regularity":0.0,"avg_price_deviation":0.008761089447010447,"quote_to_trade_ratio":1.0,"latency_cancel_interaction":0.0,"cancel_intensity_ratio":0.0,"fill_cancel_interaction":0.0,"trader_type":"normal","predicted_trader_type":0},{"user_id":7,"cancel_rate":0.0,"zero_fill_cancel_rate":0.0,"cancel_to_order_ratio":0.0,"avg_fill_ratio":1.0,"min_fill_ratio":1.0,"avg_time_to_cancel":-1773385.3516999222,"min_time_to_cancel":-1773385.351703847,"std_time_to_cancel":3.4468703874708053e-06,"limit_order_ratio":0.0,"market_order_ratio":0.0,"self_trade_count":0,"both_sides_manip":0,"avg_engine_latency":3.9e-08,"max_engine_latency":7.9e-08,"unique_sides":1,"unique_instruments":1,"order_book_imbalance":1.0,"cancel_timing_regularity":0.0,"avg_price_deviation":0.0,"quote_to_trade_ratio":1.0,"latency_cancel_interaction":0.0,"cancel_intensity_ratio":0.0,"fill_cancel_interaction":0.0,"trader_type":"normal","predicted_trader_type":0},{"user_id":11,"cancel_rate":0.0,"zero_fill_cancel_rate":0.0,"cancel_to_order_ratio":0.0,"avg_fill_ratio":1.0,"min_fill_ratio":1.0,"avg_time_to_cancel":-1773385.351697834,"min_time_to_cancel":-1773385.351697834,"std_time_to_cancel":0.0,"limit_order_ratio":0.0,"market_order_ratio":0.0,"self_trade_count":0,"both_sides_manip":0,"avg_engine_latency":2.14e-07,"max_engine_latency":2.14e-07,"unique_sides":1,"unique_instruments":1,"order_book_imbalance":1.0,"cancel_timing_regularity":0.0,"avg_price_deviation":0.003692717865931378,"quote_to_trade_ratio":1.0,"latency_cancel_interaction":0.0,"cancel_intensity_ratio":0.0,"fill_cancel_interaction":0.0,"trader_type":"normal","predicted_trader_type":0},{"user_id":17,"cancel_rate":0.0,"zero_fill_cancel_rate":0.0,"cancel_to_order_ratio":0.0,"avg_fill_ratio":1.0,"min_fill_ratio":1.0,"avg_time_to_cancel":-1773385.351702726,"min_time_to_cancel":-1773385.351702726,"std_time_to_cancel":0.0,"limit_order_ratio":1.0,"market_order_ratio":0.0,"self_trade_count":0,"both_sides_manip":0,"avg_engine_latency":2.7e-08,"max_engine_latency":2.7e-08,"unique_sides":1,"unique_instruments":1,"order_book_imbalance":1.0,"cancel_timing_regularity":0.0,"avg_price_deviation":0.0019103613706839,"quote_to_trade_ratio":1.0,"latency_cancel_interaction":0.0,"cancel_intensity_ratio":0.0,"fill_cancel_interaction":0.0,"trader_type":"normal","predicted_trader_type":0},{"user_id":18,"cancel_rate":0.0,"zero_fill_cancel_rate":0.0,"cancel_to_order_ratio":0.0,"avg_fill_ratio":1.0,"min_fill_ratio":1.0,"avg_time_to_cancel":-1773385.351702923,"min_time_to_cancel":-1773385.351703355,"std_time_to_cancel":6.108823436711781e-07,"limit_order_ratio":0.0,"market_order_ratio":0.0,"self_trade_count":0,"both_sides_manip":0,"avg_engine_latency":1.3e-08,"max_engine_latency":1.4e-08,"unique_sides":1,"unique_instruments":1,"order_book_imbalance":1.0,"cancel_timing_regularity":0.0,"avg_price_deviation":0.0003805029068129644,"quote_to_trade_ratio":1.0,"latency_cancel_interaction":0.0,"cancel_intensity_ratio":0.0,"fill_cancel_interaction":0.0,"trader_type":"normal","predicted_trader_type":0},{"user_id":20,"cancel_rate":0.0,"zero_fill_cancel_rate":0.0,"cancel_to_order_ratio":0.0,"avg_fill_ratio":1.0,"min_fill_ratio":1.0,"avg_time_to_cancel":-1773385.351701084,"min_time_to_cancel":-1773385.351701084,"std_time_to_cancel":0.0,"limit_order_ratio":0.0,"market_order_ratio":0.0,"self_trade_count":0,"both_sides_manip":0,"avg_engine_latency":1.3e-08,"max_engine_latency":1.3e-08,"unique_sides":1,"unique_instruments":1,"order_book_imbalance":1.0,"cancel_timing_regularity":0.0,"avg_price_deviation":7.966906374231431e-05,"quote_to_trade_ratio":1.0,"latency_cancel_interaction":0.0,"cancel_intensity_ratio":0.0,"fill_cancel_interaction":0.0,"trader_type":"normal","predicted_trader_type":0},{"user_id":21,"cancel_rate":0.0,"zero_fill_cancel_rate":0.0,"cancel_to_order_ratio":0.0,"avg_fill_ratio":1.0,"min_fill_ratio":1.0,"avg_time_to_cancel":-1773385.351703376,"min_time_to_cancel":-1773385.351703376,"std_time_to_cancel":0.0,"limit_order_ratio":0.0,"market_order_ratio":0.0,"self_trade_count":0,"both_sides_manip":0,"avg_engine_latency":1.1e-08,"max_engine_latency":1.1e-08,"unique_sides":1,"unique_instruments":1,"order_book_imbalance":1.0,"cancel_timing_regularity":0.0,"avg_price_deviation":0.0003805029068129644,"quote_to_trade_ratio":1.0,"latency_cancel_interaction":0.0,"cancel_intensity_ratio":0.0,"fill_cancel_interaction":0.0,"trader_type":"normal","predicted_trader_type":0},{"user_id":24,"cancel_rate":0.0,"zero_fill_cancel_rate":0.0,"cancel_to_order_ratio":0.0,"avg_fill_ratio":1.0,"min_fill_ratio":1.0,"avg_time_to_cancel":-1773385.3517024461,"min_time_to_cancel":-1773385.351702468,"std_time_to_cancel":3.119843746646395e-08,"limit_order_ratio":0.0,"market_order_ratio":0.0,"self_trade_count":0,"both_sides_manip":0,"avg_engine_latency":1.4e-08,"max_engine_latency":1.6e-08,"unique_sides":1,"unique_instruments":1,"order_book_imbalance":1.0,"cancel_timing_regularity":0.0,"avg_price_deviation":0.0003805029068129644,"quote_to_trade_ratio":1.0,"latency_cancel_interaction":0.0,"cancel_intensity_ratio":0.0,"fill_cancel_interaction":0.0,"trader_type":"normal","predicted_trader_type":0},{"user_id":92,"cancel_rate":0.0,"zero_fill_cancel_rate":0.0,"cancel_to_order_ratio":0.0,"avg_fill_ratio":1.0,"min_fill_ratio":1.0,"avg_time_to_cancel":-1773385.3517012685,"min_time_to_cancel":-1773385.351701431,"std_time_to_cancel":2.2983203328596902e-07,"limit_order_ratio":0.0,"market_order_ratio":0.0,"self_trade_count":0,"both_sides_manip":0,"avg_engine_latency":1.4e-08,"max_engine_latency":1.5e-08,"unique_sides":1,"unique_instruments":1,"order_book_imbalance":1.0,"cancel_timing_regularity":0.0,"avg_price_deviation":0.0003253983068698379,"quote_to_trade_ratio":1.0,"latency_cancel_interaction":0.0,"cancel_intensity_ratio":0.0,"fill_cancel_interaction":0.0,"trader_type":"normal","predicted_trader_type":0},{"user_id":93,"cancel_rate":0.0,"zero_fill_cancel_rate":0.0,"cancel_to_order_ratio":0.0,"avg_fill_ratio":1.0,"min_fill_ratio":1.0,"avg_time_to_cancel":-1773385.3517020908,"min_time_to_cancel":-1773385.351702397,"std_time_to_cancel":4.212680873050132e-07,"limit_order_ratio":0.0,"market_order_ratio":0.0,"self_trade_count":0,"both_sides_manip":0,"avg_engine_latency":2.75e-08,"max_engine_latency":6.7e-08,"unique_sides":1,"unique_instruments":1,"order_book_imbalance":1.0,"cancel_timing_regularity":0.0,"avg_price_deviation":0.0003253983068698379,"quote_to_trade_ratio":1.0,"latency_cancel_interaction":0.0,"cancel_intensity_ratio":0.0,"fill_cancel_interaction":0.0,"trader_type":"normal","predicted_trader_type":0},{"user_id":98,"cancel_rate":0.0,"zero_fill_cancel_rate":0.0,"cancel_to_order_ratio":0.0,"avg_fill_ratio":1.0,"min_fill_ratio":1.0,"avg_time_to_cancel":-1773385.351697761,"min_time_to_cancel":-1773385.351697761,"std_time_to_cancel":0.0,"limit_order_ratio":0.0,"market_order_ratio":0.0,"self_trade_count":0,"both_sides_manip":0,"avg_engine_latency":1.3e-08,"max_engine_latency":1.3e-08,"unique_sides":1,"unique_instruments":1,"order_book_imbalance":1.0,"cancel_timing_regularity":0.0,"avg_price_deviation":0.0019147527249340425,"quote_to_trade_ratio":1.0,"latency_cancel_interaction":0.0,"cancel_intensity_ratio":0.0,"fill_cancel_interaction":0.0,"trader_type":"normal","predicted_trader_type":0},{"user_id":122,"cancel_rate":0.0,"zero_fill_cancel_rate":0.0,"cancel_to_order_ratio":0.0,"avg_fill_ratio":1.0,"min_fill_ratio":1.0,"avg_time_to_cancel":-1773385.3516982347,"min_time_to_cancel":-1773385.351698535,"std_time_to_cancel":3.9133325148763463e-07,"limit_order_ratio":0.0,"market_order_ratio":0.0,"self_trade_count":0,"both_sides_manip":0,"avg_engine_latency":1.5533333333333332e-07,"max_engine_latency":4.38e-07,"unique_sides":1,"unique_instruments":1,"order_book_imbalance":1.0,"cancel_timing_regularity":0.0,"avg_price_deviation":0.0014109952016497583,"quote_to_trade_ratio":1.0,"latency_cancel_interaction":0.0,"cancel_intensity_ratio":0.0,"fill_cancel_interaction":0.0,"trader_type":"normal","predicted_trader_type":0},{"user_id":130,"cancel_rate":0.0,"zero_fill_cancel_rate":0.0,"cancel_to_order_ratio":0.0,"avg_fill_ratio":1.0,"min_fill_ratio":1.0,"avg_time_to_cancel":-1773385.3517001162,"min_time_to_cancel":-1773385.351701058,"std_time_to_cancel":1.0461864449356533e-06,"limit_order_ratio":0.0,"market_order_ratio":0.0,"self_trade_count":0,"both_sides_manip":0,"avg_engine_latency":1.7333333333333333e-08,"max_engine_latency":2e-08,"unique_sides":1,"unique_instruments":1,"order_book_imbalance":1.0,"cancel_timing_regularity":0.0,"avg_price_deviation":0.00011208094364814062,"quote_to_trade_ratio":1.0,"latency_cancel_interaction":0.0,"cancel_intensity_ratio":0.0,"fill_cancel_interaction":0.0,"trader_type":"normal","predicted_trader_type":0},{"user_id":131,"cancel_rate":0.0,"zero_fill_cancel_rate":0.0,"cancel_to_order_ratio":0.0,"avg_fill_ratio":1.0,"min_fill_ratio":1.0,"avg_time_to_cancel":-1773385.351698157,"min_time_to_cancel":-1773385.351698157,"std_time_to_cancel":0.0,"limit_order_ratio":0.0,"market_order_ratio":0.0,"self_trade_count":0,"both_sides_manip":0,"avg_engine_latency":1.99e-07,"max_engine_latency":1.99e-07,"unique_sides":1,"unique_instruments":1,"order_book_imbalance":1.0,"cancel_timing_regularity":0.0,"avg_price_deviation":0.012714212395739602,"quote_to_trade_ratio":1.0,"latency_cancel_interaction":0.0,"cancel_intensity_ratio":0.0,"fill_cancel_interaction":0.0,"trader_type":"normal","predicted_trader_type":0},{"user_id":148,"cancel_rate":0.0,"zero_fill_cancel_rate":0.0,"cancel_to_order_ratio":0.0,"avg_fill_ratio":1.0,"min_fill_ratio":1.0,"avg_time_to_cancel":-1773385.351697727,"min_time_to_cancel":-1773385.351697727,"std_time_to_cancel":0.0,"limit_order_ratio":0.0,"market_order_ratio":0.0,"self_trade_count":0,"both_sides_manip":0,"avg_engine_latency":2.5e-08,"max_engine_latency":2.5e-08,"unique_sides":1,"unique_instruments":1,"order_book_imbalance":1.0,"cancel_timing_regularity":0.0,"avg_price_deviation":0.002274493763169456,"quote_to_trade_ratio":1.0,"latency_cancel_interaction":0.0,"cancel_intensity_ratio":0.0,"fill_cancel_interaction":0.0,"trader_type":"normal","predicted_trader_type":0},{"user_id":162,"cancel_rate":0.0,"zero_fill_cancel_rate":0.0,"cancel_to_order_ratio":0.0,"avg_fill_ratio":1.0,"min_fill_ratio":1.0,"avg_time_to_cancel":-1773385.351703394,"min_time_to_cancel":-1773385.351703394,"std_time_to_cancel":0.0,"limit_order_ratio":0.0,"market_order_ratio":0.0,"self_trade_count":0,"both_sides_manip":0,"avg_engine_latency":1.2e-08,"max_engine_latency":1.2e-08,"unique_sides":1,"unique_instruments":1,"order_book_imbalance":1.0,"cancel_timing_regularity":0.0,"avg_price_deviation":0.0015238596120369303,"quote_to_trade_ratio":1.0,"latency_cancel_interaction":0.0,"cancel_intensity_ratio":0.0,"fill_cancel_interaction":0.0,"trader_type":"normal","predicted_trader_type":0},{"user_id":168,"cancel_rate":0.0,"zero_fill_cancel_rate":0.0,"cancel_to_order_ratio":0.0,"avg_fill_ratio":1.0,"min_fill_ratio":1.0,"avg_time_to_cancel":-1773385.3517030254,"min_time_to_cancel":-1773385.351703323,"std_time_to_cancel":4.205629783542824e-07,"limit_order_ratio":0.0,"market_order_ratio":0.0,"self_trade_count":0,"both_sides_manip":0,"avg_engine_latency":1.8999999999999998e-08,"max_engine_latency":2e-08,"unique_sides":1,"unique_instruments":1,"order_book_imbalance":1.0,"cancel_timing_regularity":0.0,"avg_price_deviation":0.008347038988697169,"quote_to_trade_ratio":1.0,"latency_cancel_interaction":0.0,"cancel_intensity_ratio":0.0,"fill_cancel_interaction":0.0,"trader_type":"normal","predicted_trader_type":0},{"user_id":176,"cancel_rate":0.0,"zero_fill_cancel_rate":0.0,"cancel_to_order_ratio":0.0,"avg_fill_ratio":1.0,"min_fill_ratio":1.0,"avg_time_to_cancel":-1773385.3516978496,"min_time_to_cancel":-1773385.351697866,"std_time_to_cancel":2.3378330033386533e-08,"limit_order_ratio":0.0,"market_order_ratio":0.0,"self_trade_count":0,"both_sides_manip":0,"avg_engine_latency":2.95e-08,"max_engine_latency":3.8e-08,"unique_sides":1,"unique_instruments":1,"order_book_imbalance":1.0,"cancel_timing_regularity":0.0,"avg_price_deviation":0.00834762369131499,"quote_to_trade_ratio":1.0,"latency_cancel_interaction":0.0,"cancel_intensity_ratio":0.0,"fill_cancel_interaction":0.0,"trader_type":"normal","predicted_trader_type":0},{"user_id":194,"cancel_rate":0.0,"zero_fill_cancel_rate":0.0,"cancel_to_order_ratio":0.0,"avg_fill_ratio":1.0,"min_fill_ratio":1.0,"avg_time_to_cancel":-1773385.351702206,"min_time_to_cancel":-1773385.351702206,"std_time_to_cancel":0.0,"limit_order_ratio":0.0,"market_order_ratio":0.0,"self_trade_count":0,"both_sides_manip":0,"avg_engine_latency":1.8e-08,"max_engine_latency":1.8e-08,"unique_sides":1,"unique_instruments":1,"order_book_imbalance":1.0,"cancel_timing_regularity":0.0,"avg_price_deviation":7.966906374218255e-05,"quote_to_trade_ratio":1.0,"latency_cancel_interaction":0.0,"cancel_intensity_ratio":0.0,"fill_cancel_interaction":0.0,"trader_type":"normal","predicted_trader_type":0},{"user_id":236,"cancel_rate":0.0,"zero_fill_cancel_rate":0.0,"cancel_to_order_ratio":0.0,"avg_fill_ratio":1.0,"min_fill_ratio":1.0,"avg_time_to_cancel":-1773385.3516986414,"min_time_to_cancel":-1773385.351698652,"std_time_to_cancel":1.4817251429611184e-08,"limit_order_ratio":0.0,"market_order_ratio":0.0,"self_trade_count":0,"both_sides_manip":0,"avg_engine_latency":1.2e-08,"max_engine_latency":1.4e-08,"unique_sides":1,"unique_instruments":1,"order_book_imbalance":1.0,"cancel_timing_regularity":0.0,"avg_price_deviation":0.0021134902367852706,"quote_to_trade_ratio":1.0,"latency_cancel_interaction":0.0,"cancel_intensity_ratio":0.0,"fill_cancel_interaction":0.0,"trader_type":"normal","predicted_trader_type":0},{"user_id":251,"cancel_rate":0.0,"zero_fill_cancel_rate":0.0,"cancel_to_order_ratio":0.0,"avg_fill_ratio":1.0,"min_fill_ratio":1.0,"avg_time_to_cancel":-1773385.351698734,"min_time_to_cancel":-1773385.351698734,"std_time_to_cancel":0.0,"limit_order_ratio":0.0,"market_order_ratio":0.0,"self_trade_count":0,"both_sides_manip":0,"avg_engine_latency":1.4e-08,"max_engine_latency":1.4e-08,"unique_sides":1,"unique_instruments":1,"order_book_imbalance":1.0,"cancel_timing_regularity":0.0,"avg_price_deviation":0.0021134902367852706,"quote_to_trade_ratio":1.0,"latency_cancel_interaction":0.0,"cancel_intensity_ratio":0.0,"fill_cancel_interaction":0.0,"trader_type":"normal","predicted_trader_type":0},{"user_id":286,"cancel_rate":0.0,"zero_fill_cancel_rate":0.0,"cancel_to_order_ratio":0.0,"avg_fill_ratio":1.0,"min_fill_ratio":1.0,"avg_time_to_cancel":-1773385.351701891,"min_time_to_cancel":-1773385.351701891,"std_time_to_cancel":0.0,"limit_order_ratio":0.0,"market_order_ratio":0.0,"self_trade_count":0,"both_sides_manip":0,"avg_engine_latency":2.1e-08,"max_engine_latency":2.1e-08,"unique_sides":1,"unique_instruments":1,"order_book_imbalance":1.0,"cancel_timing_regularity":0.0,"avg_price_deviation":0.0,"quote_to_trade_ratio":1.0,"latency_cancel_interaction":0.0,"cancel_intensity_ratio":0.0,"fill_cancel_interaction":0.0,"trader_type":"normal","predicted_trader_type":0},{"user_id":349,"cancel_rate":0.0,"zero_fill_cancel_rate":0.0,"cancel_to_order_ratio":0.0,"avg_fill_ratio":1.0,"min_fill_ratio":1.0,"avg_time_to_cancel":-1773385.3516986365,"min_time_to_cancel":-1773385.351699195,"std_time_to_cancel":7.899241373252717e-07,"limit_order_ratio":0.0,"market_order_ratio":0.0,"self_trade_count":0,"both_sides_manip":0,"avg_engine_latency":2.4e-07,"max_engine_latency":4.39e-07,"unique_sides":1,"unique_instruments":1,"order_book_imbalance":1.0,"cancel_timing_regularity":0.0,"avg_price_deviation":0.005603876550472035,"quote_to_trade_ratio":1.0,"latency_cancel_interaction":0.0,"cancel_intensity_ratio":0.0,"fill_cancel_interaction":0.0,"trader_type":"normal","predicted_trader_type":0},{"user_id":359,"cancel_rate":0.0,"zero_fill_cancel_rate":0.0,"cancel_to_order_ratio":0.0,"avg_fill_ratio":1.0,"min_fill_ratio":1.0,"avg_time_to_cancel":-1773385.351697397,"min_time_to_cancel":-1773385.351697438,"std_time_to_cancel":5.795191670247929e-08,"limit_order_ratio":0.0,"market_order_ratio":0.0,"self_trade_count":0,"both_sides_manip":0,"avg_engine_latency":2e-08,"max_engine_latency":2.1e-08,"unique_sides":1,"unique_instruments":1,"order_book_imbalance":1.0,"cancel_timing_regularity":0.0,"avg_price_deviation":0.0021134902367852706,"quote_to_trade_ratio":1.0,"latency_cancel_interaction":0.0,"cancel_intensity_ratio":0.0,"fill_cancel_interaction":0.0,"trader_type":"normal","predicted_trader_type":0},{"user_id":398,"cancel_rate":0.0,"zero_fill_cancel_rate":0.0,"cancel_to_order_ratio":0.0,"avg_fill_ratio":1.0,"min_fill_ratio":1.0,"avg_time_to_cancel":-1773385.351703658,"min_time_to_cancel":-1773385.351703658,"std_time_to_cancel":0.0,"limit_order_ratio":0.0,"market_order_ratio":0.0,"self_trade_count":0,"both_sides_manip":0,"avg_engine_latency":1.8e-08,"max_engine_latency":1.8e-08,"unique_sides":1,"unique_instruments":1,"order_book_imbalance":1.0,"cancel_timing_regularity":0.0,"avg_price_deviation":0.00048648811906353495,"quote_to_trade_ratio":1.0,"latency_cancel_interaction":0.0,"cancel_intensity_ratio":0.0,"fill_cancel_interaction":0.0,"trader_type":"normal","predicted_trader_type":0},{"user_id":416,"cancel_rate":0.0,"zero_fill_cancel_rate":0.0,"cancel_to_order_ratio":0.0,"avg_fill_ratio":1.0,"min_fill_ratio":1.0,"avg_time_to_cancel":-1773385.351697667,"min_time_to_cancel":-1773385.351697667,"std_time_to_cancel":0.0,"limit_order_ratio":0.0,"market_order_ratio":0.0,"self_trade_count":0,"both_sides_manip":0,"avg_engine_latency":1.6e-08,"max_engine_latency":1.6e-08,"unique_sides":1,"unique_instruments":1,"order_book_imbalance":1.0,"cancel_timing_regularity":0.0,"avg_price_deviation":0.0009196511144368561,"quote_to_trade_ratio":1.0,"latency_cancel_interaction":0.0,"cancel_intensity_ratio":0.0,"fill_cancel_interaction":0.0,"trader_type":"normal","predicted_trader_type":0},{"user_id":425,"cancel_rate":0.0,"zero_fill_cancel_rate":0.0,"cancel_to_order_ratio":0.0,"avg_fill_ratio":1.0,"min_fill_ratio":1.0,"avg_time_to_cancel":-1773385.351697927,"min_time_to_cancel":-1773385.351697927,"std_time_to_cancel":0.0,"limit_order_ratio":1.0,"market_order_ratio":0.0,"self_trade_count":0,"both_sides_manip":0,"avg_engine_latency":4.18e-07,"max_engine_latency":4.18e-07,"unique_sides":1,"unique_instruments":1,"order_book_imbalance":1.0,"cancel_timing_regularity":0.0,"avg_price_deviation":0.008015971989671113,"quote_to_trade_ratio":1.0,"latency_cancel_interaction":0.0,"cancel_intensity_ratio":0.0,"fill_cancel_interaction":0.0,"trader_type":"normal","predicted_trader_type":0},{"user_id":544,"cancel_rate":0.0,"zero_fill_cancel_rate":0.0,"cancel_to_order_ratio":0.0,"avg_fill_ratio":1.0,"min_fill_ratio":1.0,"avg_time_to_cancel":-1773385.351697246,"min_time_to_cancel":-1773385.351697246,"std_time_to_cancel":0.0,"limit_order_ratio":0.0,"market_order_ratio":0.0,"self_trade_count":0,"both_sides_manip":0,"avg_engine_latency":1.3e-08,"max_engine_latency":1.3e-08,"unique_sides":1,"unique_instruments":1,"order_book_imbalance":1.0,"cancel_timing_regularity":0.0,"avg_price_deviation":0.01595084222099436,"quote_to_trade_ratio":1.0,"latency_cancel_interaction":0.0,"cancel_intensity_ratio":0.0,"fill_cancel_interaction":0.0,"trader_type":"normal","predicted_trader_type":0},{"user_id":549,"cancel_rate":0.0,"zero_fill_cancel_rate":0.0,"cancel_to_order_ratio":0.0,"avg_fill_ratio":1.0,"min_fill_ratio":1.0,"avg_time_to_cancel":-1773385.351703769,"min_time_to_cancel":-1773385.351703769,"std_time_to_cancel":0.0,"limit_order_ratio":0.0,"market_order_ratio":0.0,"self_trade_count":0,"both_sides_manip":0,"avg_engine_latency":1.4e-08,"max_engine_latency":1.4e-08,"unique_sides":1,"unique_instruments":1,"order_book_imbalance":1.0,"cancel_timing_regularity":0.0,"avg_price_deviation":0.004478375517244337,"quote_to_trade_ratio":1.0,"latency_cancel_interaction":0.0,"cancel_intensity_ratio":0.0,"fill_cancel_interaction":0.0,"trader_type":"normal","predicted_trader_type":0},{"user_id":565,"cancel_rate":0.0,"zero_fill_cancel_rate":0.0,"cancel_to_order_ratio":0.0,"avg_fill_ratio":1.0,"min_fill_ratio":1.0,"avg_time_to_cancel":-1773385.351697397,"min_time_to_cancel":-1773385.351697397,"std_time_to_cancel":0.0,"limit_order_ratio":0.0,"market_order_ratio":0.0,"self_trade_count":0,"both_sides_manip":0,"avg_engine_latency":1.43e-07,"max_engine_latency":1.43e-07,"unique_sides":1,"unique_instruments":1,"order_book_imbalance":1.0,"cancel_timing_regularity":0.0,"avg_price_deviation":0.0021491741188929296,"quote_to_trade_ratio":1.0,"latency_cancel_interaction":0.0,"cancel_intensity_ratio":0.0,"fill_cancel_interaction":0.0,"trader_type":"normal","predicted_trader_type":0},{"user_id":579,"cancel_rate":0.0,"zero_fill_cancel_rate":0.0,"cancel_to_order_ratio":0.0,"avg_fill_ratio":1.0,"min_fill_ratio":1.0,"avg_time_to_cancel":-1773385.3516997753,"min_time_to_cancel":-1773385.351703705,"std_time_to_cancel":3.4052963678623616e-06,"limit_order_ratio":0.0,"market_order_ratio":0.0,"self_trade_count":0,"both_sides_manip":0,"avg_engine_latency":2.8e-08,"max_engine_latency":5.3e-08,"unique_sides":1,"unique_instruments":1,"order_book_imbalance":1.0,"cancel_timing_regularity":0.0,"avg_price_deviation":0.000919651114436856,"quote_to_trade_ratio":1.0,"latency_cancel_interaction":0.0,"cancel_intensity_ratio":0.0,"fill_cancel_interaction":0.0,"trader_type":"normal","predicted_trader_type":0},{"user_id":581,"cancel_rate":0.0,"zero_fill_cancel_rate":0.0,"cancel_to_order_ratio":0.0,"avg_fill_ratio":1.0,"min_fill_ratio":1.0,"avg_time_to_cancel":-1773385.351698221,"min_time_to_cancel":-1773385.351698221,"std_time_to_cancel":0.0,"limit_order_ratio":0.0,"market_order_ratio":0.0,"self_trade_count":0,"both_sides_manip":0,"avg_engine_latency":1.7e-08,"max_engine_latency":1.7e-08,"unique_sides":1,"unique_instruments":1,"order_book_imbalance":1.0,"cancel_timing_regularity":0.0,"avg_price_deviation":0.01595084222099436,"quote_to_trade_ratio":1.0,"latency_cancel_interaction":0.0,"cancel_intensity_ratio":0.0,"fill_cancel_interaction":0.0,"trader_type":"normal","predicted_trader_type":0},{"user_id":599,"cancel_rate":0.0,"zero_fill_cancel_rate":0.0,"cancel_to_order_ratio":0.0,"avg_fill_ratio":1.0,"min_fill_ratio":1.0,"avg_time_to_cancel":-1773385.351698254,"min_time_to_cancel":-1773385.351698254,"std_time_to_cancel":0.0,"limit_order_ratio":0.0,"market_order_ratio":0.0,"self_trade_count":0,"both_sides_manip":0,"avg_engine_latency":1.5e-08,"max_engine_latency":1.5e-08,"unique_sides":1,"unique_instruments":1,"order_book_imbalance":1.0,"cancel_timing_regularity":0.0,"avg_price_deviation":0.01595084222099436,"quote_to_trade_ratio":1.0,"latency_cancel_interaction":0.0,"cancel_intensity_ratio":0.0,"fill_cancel_interaction":0.0,"trader_type":"normal","predicted_trader_type":0},{"user_id":617,"cancel_rate":0.0,"zero_fill_cancel_rate":0.0,"cancel_to_order_ratio":0.0,"avg_fill_ratio":1.0,"min_fill_ratio":1.0,"avg_time_to_cancel":-1773385.351700772,"min_time_to_cancel":-1773385.351700772,"std_time_to_cancel":0.0,"limit_order_ratio":0.0,"market_order_ratio":0.0,"self_trade_count":0,"both_sides_manip":0,"avg_engine_latency":1.26e-07,"max_engine_latency":1.26e-07,"unique_sides":1,"unique_instruments":1,"order_book_imbalance":1.0,"cancel_timing_regularity":0.0,"avg_price_deviation":0.0020001670190986573,"quote_to_trade_ratio":1.0,"latency_cancel_interaction":0.0,"cancel_intensity_ratio":0.0,"fill_cancel_interaction":0.0,"trader_type":"normal","predicted_trader_type":0},{"user_id":619,"cancel_rate":0.0,"zero_fill_cancel_rate":0.0,"cancel_to_order_ratio":0.0,"avg_fill_ratio":1.0,"min_fill_ratio":1.0,"avg_time_to_cancel":-1773385.351700908,"min_time_to_cancel":-1773385.351700908,"std_time_to_cancel":0.0,"limit_order_ratio":0.0,"market_order_ratio":0.0,"self_trade_count":0,"both_sides_manip":0,"avg_engine_latency":1.3e-08,"max_engine_latency":1.3e-08,"unique_sides":1,"unique_instruments":1,"order_book_imbalance":1.0,"cancel_timing_regularity":0.0,"avg_price_deviation":0.0020001670190986573,"quote_to_trade_ratio":1.0,"latency_cancel_interaction":0.0,"cancel_intensity_ratio":0.0,"fill_cancel_interaction":0.0,"trader_type":"normal","predicted_trader_type":0},{"user_id":623,"cancel_rate":0.0,"zero_fill_cancel_rate":0.0,"cancel_to_order_ratio":0.0,"avg_fill_ratio":1.0,"min_fill_ratio":1.0,"avg_time_to_cancel":-1773385.3517013704,"min_time_to_cancel":-1773385.351701554,"std_time_to_cancel":2.5946653614519136e-07,"limit_order_ratio":0.0,"market_order_ratio":0.0,"self_trade_count":0,"both_sides_manip":0,"avg_engine_latency":1.7e-08,"max_engine_latency":1.7e-08,"unique_sides":1,"unique_instruments":1,"order_book_imbalance":1.0,"cancel_timing_regularity":0.0,"avg_price_deviation":0.0020001670190986573,"quote_to_trade_ratio":1.0,"latency_cancel_interaction":0.0,"cancel_intensity_ratio":0.0,"fill_cancel_interaction":0.0,"trader_type":"normal","predicted_trader_type":0},{"user_id":625,"cancel_rate":0.0,"zero_fill_cancel_rate":0.0,"cancel_to_order_ratio":0.0,"avg_fill_ratio":1.0,"min_fill_ratio":1.0,"avg_time_to_cancel":-1773385.351700751,"min_time_to_cancel":-1773385.351700751,"std_time_to_cancel":0.0,"limit_order_ratio":0.0,"market_order_ratio":0.0,"self_trade_count":0,"both_sides_manip":0,"avg_engine_latency":1.2e-08,"max_engine_latency":1.2e-08,"unique_sides":1,"unique_instruments":1,"order_book_imbalance":1.0,"cancel_timing_regularity":0.0,"avg_price_deviation":0.0020000001522659594,"quote_to_trade_ratio":1.0,"latency_cancel_interaction":0.0,"cancel_intensity_ratio":0.0,"fill_cancel_interaction":0.0,"trader_type":"normal","predicted_trader_type":0},{"user_id":636,"cancel_rate":0.0,"zero_fill_cancel_rate":0.0,"cancel_to_order_ratio":0.0,"avg_fill_ratio":1.0,"min_fill_ratio":1.0,"avg_time_to_cancel":-1773385.351700442,"min_time_to_cancel":-1773385.351700442,"std_time_to_cancel":0.0,"limit_order_ratio":0.0,"market_order_ratio":0.0,"self_trade_count":0,"both_sides_manip":0,"avg_engine_latency":1.4e-08,"max_engine_latency":1.4e-08,"unique_sides":1,"unique_instruments":1,"order_book_imbalance":1.0,"cancel_timing_regularity":0.0,"avg_price_deviation":0.0014677356299193122,"quote_to_trade_ratio":1.0,"latency_cancel_interaction":0.0,"cancel_intensity_ratio":0.0,"fill_cancel_interaction":0.0,"trader_type":"normal","predicted_trader_type":0},{"user_id":637,"cancel_rate":0.0,"zero_fill_cancel_rate":0.0,"cancel_to_order_ratio":0.0,"avg_fill_ratio":1.0,"min_fill_ratio":1.0,"avg_time_to_cancel":-1773385.351700727,"min_time_to_cancel":-1773385.351700727,"std_time_to_cancel":0.0,"limit_order_ratio":0.0,"market_order_ratio":0.0,"self_trade_count":0,"both_sides_manip":0,"avg_engine_latency":1.6e-08,"max_engine_latency":1.6e-08,"unique_sides":1,"unique_instruments":1,"order_book_imbalance":1.0,"cancel_timing_regularity":0.0,"avg_price_deviation":0.0014677356299193122,"quote_to_trade_ratio":1.0,"latency_cancel_interaction":0.0,"cancel_intensity_ratio":0.0,"fill_cancel_interaction":0.0,"trader_type":"normal","predicted_trader_type":0},{"user_id":689,"cancel_rate":0.0,"zero_fill_cancel_rate":0.0,"cancel_to_order_ratio":0.0,"avg_fill_ratio":1.0,"min_fill_ratio":1.0,"avg_time_to_cancel":-1773385.351703473,"min_time_to_cancel":-1773385.351703473,"std_time_to_cancel":0.0,"limit_order_ratio":0.0,"market_order_ratio":0.0,"self_trade_count":0,"both_sides_manip":0,"avg_engine_latency":1.4e-08,"max_engine_latency":1.4e-08,"unique_sides":1,"unique_instruments":1,"order_book_imbalance":1.0,"cancel_timing_regularity":0.0,"avg_price_deviation":0.0,"quote_to_trade_ratio":1.0,"latency_cancel_interaction":0.0,"cancel_intensity_ratio":0.0,"fill_cancel_interaction":0.0,"trader_type":"normal","predicted_trader_type":0},{"user_id":693,"cancel_rate":0.0,"zero_fill_cancel_rate":0.0,"cancel_to_order_ratio":0.0,"avg_fill_ratio":1.0,"min_fill_ratio":1.0,"avg_time_to_cancel":-1773385.35170125,"min_time_to_cancel":-1773385.35170125,"std_time_to_cancel":0.0,"limit_order_ratio":0.0,"market_order_ratio":0.0,"self_trade_count":0,"both_sides_manip":0,"avg_engine_latency":1.9e-08,"max_engine_latency":1.9e-08,"unique_sides":1,"unique_instruments":1,"order_book_imbalance":1.0,"cancel_timing_regularity":0.0,"avg_price_deviation":0.0,"quote_to_trade_ratio":1.0,"latency_cancel_interaction":0.0,"cancel_intensity_ratio":0.0,"fill_cancel_interaction":0.0,"trader_type":"normal","predicted_trader_type":0},{"user_id":716,"cancel_rate":0.0,"zero_fill_cancel_rate":0.0,"cancel_to_order_ratio":0.0,"avg_fill_ratio":1.0,"min_fill_ratio":1.0,"avg_time_to_cancel":-1773385.3516979925,"min_time_to_cancel":-1773385.351699435,"std_time_to_cancel":9.90120663983969e-07,"limit_order_ratio":0.0,"market_order_ratio":0.0,"self_trade_count":0,"both_sides_manip":0,"avg_engine_latency":2.2e-08,"max_engine_latency":3.1e-08,"unique_sides":1,"unique_instruments":1,"order_book_imbalance":1.0,"cancel_timing_regularity":0.0,"avg_price_deviation":0.01421039511180221,"quote_to_trade_ratio":1.0,"latency_cancel_interaction":0.0,"cancel_intensity_ratio":0.0,"fill_cancel_interaction":0.0,"trader_type":"normal","predicted_trader_type":0},{"user_id":726,"cancel_rate":0.0,"zero_fill_cancel_rate":0.0,"cancel_to_order_ratio":0.0,"avg_fill_ratio":1.0,"min_fill_ratio":1.0,"avg_time_to_cancel":-1773385.351699468,"min_time_to_cancel":-1773385.351699468,"std_time_to_cancel":0.0,"limit_order_ratio":0.0,"market_order_ratio":0.0,"self_trade_count":0,"both_sides_manip":0,"avg_engine_latency":1.5e-08,"max_engine_latency":1.5e-08,"unique_sides":1,"unique_instruments":1,"order_book_imbalance":1.0,"cancel_timing_regularity":0.0,"avg_price_deviation":0.0006663096919280448,"quote_to_trade_ratio":1.0,"latency_cancel_interaction":0.0,"cancel_intensity_ratio":0.0,"fill_cancel_interaction":0.0,"trader_type":"normal","predicted_trader_type":0},{"user_id":736,"cancel_rate":0.0,"zero_fill_cancel_rate":0.0,"cancel_to_order_ratio":0.0,"avg_fill_ratio":1.0,"min_fill_ratio":1.0,"avg_time_to_cancel":-1773385.3516987676,"min_time_to_cancel":-1773385.351698791,"std_time_to_cancel":2.401205354249801e-08,"limit_order_ratio":0.0,"market_order_ratio":0.0,"self_trade_count":0,"both_sides_manip":0,"avg_engine_latency":1.4e-08,"max_engine_latency":1.6e-08,"unique_sides":1,"unique_instruments":1,"order_book_imbalance":1.0,"cancel_timing_regularity":0.0,"avg_price_deviation":0.019416218951569454,"quote_to_trade_ratio":1.0,"latency_cancel_interaction":0.0,"cancel_intensity_ratio":0.0,"fill_cancel_interaction":0.0,"trader_type":"normal","predicted_trader_type":0},{"user_id":742,"cancel_rate":0.0,"zero_fill_cancel_rate":0.0,"cancel_to_order_ratio":0.0,"avg_fill_ratio":1.0,"min_fill_ratio":1.0,"avg_time_to_cancel":-1773385.351701597,"min_time_to_cancel":-1773385.351701597,"std_time_to_cancel":0.0,"limit_order_ratio":0.0,"market_order_ratio":0.0,"self_trade_count":0,"both_sides_manip":0,"avg_engine_latency":1.7e-08,"max_engine_latency":1.7e-08,"unique_sides":1,"unique_instruments":1,"order_book_imbalance":1.0,"cancel_timing_regularity":0.0,"avg_price_deviation":0.0052620934215706315,"quote_to_trade_ratio":1.0,"latency_cancel_interaction":0.0,"cancel_intensity_ratio":0.0,"fill_cancel_interaction":0.0,"trader_type":"normal","predicted_trader_type":0},{"user_id":770,"cancel_rate":0.0,"zero_fill_cancel_rate":0.0,"cancel_to_order_ratio":0.0,"avg_fill_ratio":1.0,"min_fill_ratio":1.0,"avg_time_to_cancel":-1773385.351702965,"min_time_to_cancel":-1773385.351702965,"std_time_to_cancel":0.0,"limit_order_ratio":0.0,"market_order_ratio":0.0,"self_trade_count":0,"both_sides_manip":0,"avg_engine_latency":4.1e-08,"max_engine_latency":4.1e-08,"unique_sides":1,"unique_instruments":1,"order_book_imbalance":1.0,"cancel_timing_regularity":0.0,"avg_price_deviation":0.0,"quote_to_trade_ratio":1.0,"latency_cancel_interaction":0.0,"cancel_intensity_ratio":0.0,"fill_cancel_interaction":0.0,"trader_type":"normal","predicted_trader_type":0},{"user_id":783,"cancel_rate":0.0,"zero_fill_cancel_rate":0.0,"cancel_to_order_ratio":0.0,"avg_fill_ratio":1.0,"min_fill_ratio":1.0,"avg_time_to_cancel":-1773385.35170158,"min_time_to_cancel":-1773385.35170158,"std_time_to_cancel":0.0,"limit_order_ratio":0.0,"market_order_ratio":0.0,"self_trade_count":0,"both_sides_manip":0,"avg_engine_latency":9e-09,"max_engine_latency":9e-09,"unique_sides":1,"unique_instruments":1,"order_book_imbalance":1.0,"cancel_timing_regularity":0.0,"avg_price_deviation":0.003109836670775472,"quote_to_trade_ratio":1.0,"latency_cancel_interaction":0.0,"cancel_intensity_ratio":0.0,"fill_cancel_interaction":0.0,"trader_type":"normal","predicted_trader_type":0},{"user_id":796,"cancel_rate":0.0,"zero_fill_cancel_rate":0.0,"cancel_to_order_ratio":0.0,"avg_fill_ratio":1.0,"min_fill_ratio":1.0,"avg_time_to_cancel":-1773385.351700414,"min_time_to_cancel":-1773385.351700414,"std_time_to_cancel":0.0,"limit_order_ratio":0.0,"market_order_ratio":0.0,"self_trade_count":0,"both_sides_manip":0,"avg_engine_latency":1.8e-08,"max_engine_latency":1.8e-08,"unique_sides":1,"unique_instruments":1,"order_book_imbalance":1.0,"cancel_timing_regularity":0.0,"avg_price_deviation":0.006633393580151307,"quote_to_trade_ratio":1.0,"latency_cancel_interaction":0.0,"cancel_intensity_ratio":0.0,"fill_cancel_interaction":0.0,"trader_type":"normal","predicted_trader_type":0},{"user_id":818,"cancel_rate":0.0,"zero_fill_cancel_rate":0.0,"cancel_to_order_ratio":0.0,"avg_fill_ratio":0.5,"min_fill_ratio":0.0,"avg_time_to_cancel":-1773385.351699068,"min_time_to_cancel":-1773385.351699648,"std_time_to_cancel":3.8685405251263946e-07,"limit_order_ratio":0.75,"market_order_ratio":0.0,"self_trade_count":0,"both_sides_manip":1,"avg_engine_latency":2.0225e-07,"max_engine_latency":7.85e-07,"unique_sides":2,"unique_instruments":1,"order_book_imbalance":0.0,"cancel_timing_regularity":0.0,"avg_price_deviation":0.001002004051030695,"quote_to_trade_ratio":2.0,"latency_cancel_interaction":0.0,"cancel_intensity_ratio":0.0,"fill_cancel_interaction":0.0,"trader_type":"normal","predicted_trader_type":0},{"user_id":832,"cancel_rate":0.0,"zero_fill_cancel_rate":0.0,"cancel_to_order_ratio":0.0,"avg_fill_ratio":1.0,"min_fill_ratio":1.0,"avg_time_to_cancel":-1773385.3516980833,"min_time_to_cancel":-1773385.351698485,"std_time_to_cancel":5.677476779769301e-07,"limit_order_ratio":0.0,"market_order_ratio":0.0,"self_trade_count":0,"both_sides_manip":0,"avg_engine_latency":4.4e-08,"max_engine_latency":7.5e-08,"unique_sides":1,"unique_instruments":1,"order_book_imbalance":1.0,"cancel_timing_regularity":0.0,"avg_price_deviation":0.0031576705084095233,"quote_to_trade_ratio":1.0,"latency_cancel_interaction":0.0,"cancel_intensity_ratio":0.0,"fill_cancel_interaction":0.0,"trader_type":"normal","predicted_trader_type":0},{"user_id":842,"cancel_rate":0.0,"zero_fill_cancel_rate":0.0,"cancel_to_order_ratio":0.0,"avg_fill_ratio":1.0,"min_fill_ratio":1.0,"avg_time_to_cancel":-1773385.35169857,"min_time_to_cancel":-1773385.35169857,"std_time_to_cancel":0.0,"limit_order_ratio":0.0,"market_order_ratio":0.0,"self_trade_count":0,"both_sides_manip":0,"avg_engine_latency":1.4e-08,"max_engine_latency":1.4e-08,"unique_sides":1,"unique_instruments":1,"order_book_imbalance":1.0,"cancel_timing_regularity":0.0,"avg_price_deviation":0.0031576705084095233,"quote_to_trade_ratio":1.0,"latency_cancel_interaction":0.0,"cancel_intensity_ratio":0.0,"fill_cancel_interaction":0.0,"trader_type":"normal","predicted_trader_type":0},{"user_id":853,"cancel_rate":0.0,"zero_fill_cancel_rate":0.0,"cancel_to_order_ratio":0.0,"avg_fill_ratio":1.0,"min_fill_ratio":1.0,"avg_time_to_cancel":-1773385.3516986845,"min_time_to_cancel":-1773385.351698777,"std_time_to_cancel":1.3072108483456977e-07,"limit_order_ratio":0.0,"market_order_ratio":0.0,"self_trade_count":0,"both_sides_manip":0,"avg_engine_latency":7.05e-08,"max_engine_latency":1.28e-07,"unique_sides":1,"unique_instruments":1,"order_book_imbalance":1.0,"cancel_timing_regularity":0.0,"avg_price_deviation":0.0031576705084095233,"quote_to_trade_ratio":1.0,"latency_cancel_interaction":0.0,"cancel_intensity_ratio":0.0,"fill_cancel_interaction":0.0,"trader_type":"normal","predicted_trader_type":0},{"user_id":857,"cancel_rate":0.0,"zero_fill_cancel_rate":0.0,"cancel_to_order_ratio":0.0,"avg_fill_ratio":1.0,"min_fill_ratio":1.0,"avg_time_to_cancel":-1773385.351700468,"min_time_to_cancel":-1773385.351700468,"std_time_to_cancel":0.0,"limit_order_ratio":0.0,"market_order_ratio":0.0,"self_trade_count":0,"both_sides_manip":0,"avg_engine_latency":1.7e-08,"max_engine_latency":1.7e-08,"unique_sides":1,"unique_instruments":1,"order_book_imbalance":1.0,"cancel_timing_regularity":0.0,"avg_price_deviation":0.008178664229188263,"quote_to_trade_ratio":1.0,"latency_cancel_interaction":0.0,"cancel_intensity_ratio":0.0,"fill_cancel_interaction":0.0,"trader_type":"normal","predicted_trader_type":0},{"user_id":882,"cancel_rate":0.0,"zero_fill_cancel_rate":0.0,"cancel_to_order_ratio":0.0,"avg_fill_ratio":1.0,"min_fill_ratio":1.0,"avg_time_to_cancel":-1773385.351697658,"min_time_to_cancel":-1773385.351697658,"std_time_to_cancel":0.0,"limit_order_ratio":0.0,"market_order_ratio":0.0,"self_trade_count":0,"both_sides_manip":0,"avg_engine_latency":1.4e-08,"max_engine_latency":1.4e-08,"unique_sides":1,"unique_instruments":1,"order_book_imbalance":1.0,"cancel_timing_regularity":0.0,"avg_price_deviation":0.006659347553937148,"quote_to_trade_ratio":1.0,"latency_cancel_interaction":0.0,"cancel_intensity_ratio":0.0,"fill_cancel_interaction":0.0,"trader_type":"normal","predicted_trader_type":0},{"user_id":894,"cancel_rate":0.0,"zero_fill_cancel_rate":0.0,"cancel_to_order_ratio":0.0,"avg_fill_ratio":1.0,"min_fill_ratio":1.0,"avg_time_to_cancel":-1773385.351697288,"min_time_to_cancel":-1773385.351697288,"std_time_to_cancel":0.0,"limit_order_ratio":0.0,"market_order_ratio":0.0,"self_trade_count":0,"both_sides_manip":0,"avg_engine_latency":3.59e-07,"max_engine_latency":3.59e-07,"unique_sides":1,"unique_instruments":1,"order_book_imbalance":1.0,"cancel_timing_regularity":0.0,"avg_price_deviation":0.006659347553937148,"quote_to_trade_ratio":1.0,"latency_cancel_interaction":0.0,"cancel_intensity_ratio":0.0,"fill_cancel_interaction":0.0,"trader_type":"normal","predicted_trader_type":0},{"user_id":900,"cancel_rate":0.0,"zero_fill_cancel_rate":0.0,"cancel_to_order_ratio":0.0,"avg_fill_ratio":1.0,"min_fill_ratio":1.0,"avg_time_to_cancel":-1773385.3516997756,"min_time_to_cancel":-1773385.351699875,"std_time_to_cancel":1.4084618258926037e-07,"limit_order_ratio":0.0,"market_order_ratio":0.0,"self_trade_count":0,"both_sides_manip":0,"avg_engine_latency":1.5000000000000002e-08,"max_engine_latency":1.6e-08,"unique_sides":1,"unique_instruments":1,"order_book_imbalance":1.0,"cancel_timing_regularity":0.0,"avg_price_deviation":0.004597777377255234,"quote_to_trade_ratio":1.0,"latency_cancel_interaction":0.0,"cancel_intensity_ratio":0.0,"fill_cancel_interaction":0.0,"trader_type":"normal","predicted_trader_type":0},{"user_id":906,"cancel_rate":0.0,"zero_fill_cancel_rate":0.0,"cancel_to_order_ratio":0.0,"avg_fill_ratio":1.0,"min_fill_ratio":1.0,"avg_time_to_cancel":-1773385.351699921,"min_time_to_cancel":-1773385.351699921,"std_time_to_cancel":0.0,"limit_order_ratio":0.0,"market_order_ratio":0.0,"self_trade_count":0,"both_sides_manip":0,"avg_engine_latency":1.4e-08,"max_engine_latency":1.4e-08,"unique_sides":1,"unique_instruments":1,"order_book_imbalance":1.0,"cancel_timing_regularity":0.0,"avg_price_deviation":0.008697556756675193,"quote_to_trade_ratio":1.0,"latency_cancel_interaction":0.0,"cancel_intensity_ratio":0.0,"fill_cancel_interaction":0.0,"trader_type":"normal","predicted_trader_type":0},{"user_id":918,"cancel_rate":0.0,"zero_fill_cancel_rate":0.0,"cancel_to_order_ratio":0.0,"avg_fill_ratio":1.0,"min_fill_ratio":1.0,"avg_time_to_cancel":-1773385.351701415,"min_time_to_cancel":-1773385.351701415,"std_time_to_cancel":0.0,"limit_order_ratio":0.0,"market_order_ratio":0.0,"self_trade_count":0,"both_sides_manip":0,"avg_engine_latency":9.9e-08,"max_engine_latency":9.9e-08,"unique_sides":1,"unique_instruments":1,"order_book_imbalance":1.0,"cancel_timing_regularity":0.0,"avg_price_deviation":0.01576531678491433,"quote_to_trade_ratio":1.0,"latency_cancel_interaction":0.0,"cancel_intensity_ratio":0.0,"fill_cancel_interaction":0.0,"trader_type":"normal","predicted_trader_type":0},{"user_id":922,"cancel_rate":0.0,"zero_fill_cancel_rate":0.0,"cancel_to_order_ratio":0.0,"avg_fill_ratio":1.0,"min_fill_ratio":1.0,"avg_time_to_cancel":-1773385.351701208,"min_time_to_cancel":-1773385.351701393,"std_time_to_cancel":2.615244747773233e-07,"limit_order_ratio":0.0,"market_order_ratio":0.0,"self_trade_count":0,"both_sides_manip":0,"avg_engine_latency":1.35e-08,"max_engine_latency":1.4e-08,"unique_sides":1,"unique_instruments":1,"order_book_imbalance":1.0,"cancel_timing_regularity":0.0,"avg_price_deviation":0.014503946473475762,"quote_to_trade_ratio":1.0,"latency_cancel_interaction":0.0,"cancel_intensity_ratio":0.0,"fill_cancel_interaction":0.0,"trader_type":"normal","predicted_trader_type":0},{"user_id":924,"cancel_rate":0.0,"zero_fill_cancel_rate":0.0,"cancel_to_order_ratio":0.0,"avg_fill_ratio":1.0,"min_fill_ratio":1.0,"avg_time_to_cancel":-1773385.351698175,"min_time_to_cancel":-1773385.351698175,"std_time_to_cancel":0.0,"limit_order_ratio":0.0,"market_order_ratio":0.0,"self_trade_count":0,"both_sides_manip":0,"avg_engine_latency":2.58e-07,"max_engine_latency":2.58e-07,"unique_sides":1,"unique_instruments":1,"order_book_imbalance":1.0,"cancel_timing_regularity":0.0,"avg_price_deviation":0.01132021178899229,"quote_to_trade_ratio":1.0,"latency_cancel_interaction":0.0,"cancel_intensity_ratio":0.0,"fill_cancel_interaction":0.0,"trader_type":"normal","predicted_trader_type":0},{"user_id":929,"cancel_rate":0.0,"zero_fill_cancel_rate":0.0,"cancel_to_order_ratio":0.0,"avg_fill_ratio":1.0,"min_fill_ratio":1.0,"avg_time_to_cancel":-1773385.351703432,"min_time_to_cancel":-1773385.351703432,"std_time_to_cancel":0.0,"limit_order_ratio":0.0,"market_order_ratio":0.0,"self_trade_count":0,"both_sides_manip":0,"avg_engine_latency":1.7e-08,"max_engine_latency":1.7e-08,"unique_sides":1,"unique_instruments":1,"order_book_imbalance":1.0,"cancel_timing_regularity":0.0,"avg_price_deviation":0.014111792237972312,"quote_to_trade_ratio":1.0,"latency_cancel_interaction":0.0,"cancel_intensity_ratio":0.0,"fill_cancel_interaction":0.0,"trader_type":"normal","predicted_trader_type":0},{"user_id":931,"cancel_rate":0.0,"zero_fill_cancel_rate":0.0,"cancel_to_order_ratio":0.0,"avg_fill_ratio":1.0,"min_fill_ratio":1.0,"avg_time_to_cancel":-1773385.351699899,"min_time_to_cancel":-1773385.351699899,"std_time_to_cancel":0.0,"limit_order_ratio":0.0,"market_order_ratio":0.0,"self_trade_count":0,"both_sides_manip":0,"avg_engine_latency":1.3e-08,"max_engine_latency":1.3e-08,"unique_sides":1,"unique_instruments":1,"order_book_imbalance":1.0,"cancel_timing_regularity":0.0,"avg_price_deviation":0.0056429409512291735,"quote_to_trade_ratio":1.0,"latency_cancel_interaction":0.0,"cancel_intensity_ratio":0.0,"fill_cancel_interaction":0.0,"trader_type":"normal","predicted_trader_type":0},{"user_id":957,"cancel_rate":0.0,"zero_fill_cancel_rate":0.0,"cancel_to_order_ratio":0.0,"avg_fill_ratio":1.0,"min_fill_ratio":1.0,"avg_time_to_cancel":-1773385.351699341,"min_time_to_cancel":-1773385.35169962,"std_time_to_cancel":3.947151058884026e-07,"limit_order_ratio":0.0,"market_order_ratio":0.0,"self_trade_count":0,"both_sides_manip":0,"avg_engine_latency":1.85e-08,"max_engine_latency":1.9e-08,"unique_sides":1,"unique_instruments":1,"order_book_imbalance":1.0,"cancel_timing_regularity":0.0,"avg_price_deviation":0.0013006929264498081,"quote_to_trade_ratio":1.0,"latency_cancel_interaction":0.0,"cancel_intensity_ratio":0.0,"fill_cancel_interaction":0.0,"trader_type":"normal","predicted_trader_type":0},{"user_id":1000,"cancel_rate":0.0,"zero_fill_cancel_rate":0.0,"cancel_to_order_ratio":0.0,"avg_fill_ratio":1.0,"min_fill_ratio":1.0,"avg_time_to_cancel":-1773385.3516989064,"min_time_to_cancel":-1773385.351699015,"std_time_to_cancel":1.5344087035997358e-07,"limit_order_ratio":0.0,"market_order_ratio":0.0,"self_trade_count":0,"both_sides_manip":0,"avg_engine_latency":3.1999999999999995e-08,"max_engine_latency":3.6e-08,"unique_sides":1,"unique_instruments":1,"order_book_imbalance":1.0,"cancel_timing_regularity":0.0,"avg_price_deviation":0.0020040094029286294,"quote_to_trade_ratio":1.0,"latency_cancel_interaction":0.0,"cancel_intensity_ratio":0.0,"fill_cancel_interaction":0.0,"trader_type":"normal","predicted_trader_type":0},{"user_id":1003,"cancel_rate":0.0,"zero_fill_cancel_rate":0.0,"cancel_to_order_ratio":0.0,"avg_fill_ratio":1.0,"min_fill_ratio":1.0,"avg_time_to_cancel":-1773385.3517004733,"min_time_to_cancel":-1773385.351700983,"std_time_to_cancel":5.199264933234988e-07,"limit_order_ratio":0.0,"market_order_ratio":0.0,"self_trade_count":0,"both_sides_manip":0,"avg_engine_latency":1.7333333333333333e-08,"max_engine_latency":2.7e-08,"unique_sides":1,"unique_instruments":1,"order_book_imbalance":1.0,"cancel_timing_regularity":0.0,"avg_price_deviation":0.011111107786672549,"quote_to_trade_ratio":1.0,"latency_cancel_interaction":0.0,"cancel_intensity_ratio":0.0,"fill_cancel_interaction":0.0,"trader_type":"normal","predicted_trader_type":0},{"user_id":1032,"cancel_rate":0.0,"zero_fill_cancel_rate":0.0,"cancel_to_order_ratio":0.0,"avg_fill_ratio":1.0,"min_fill_ratio":1.0,"avg_time_to_cancel":-1773385.3517010123,"min_time_to_cancel":-1773385.351703924,"std_time_to_cancel":4.117302581148558e-06,"limit_order_ratio":0.0,"market_order_ratio":0.0,"self_trade_count":0,"both_sides_manip":0,"avg_engine_latency":1.55e-08,"max_engine_latency":1.6e-08,"unique_sides":1,"unique_instruments":1,"order_book_imbalance":1.0,"cancel_timing_regularity":0.0,"avg_price_deviation":0.0,"quote_to_trade_ratio":1.0,"latency_cancel_interaction":0.0,"cancel_intensity_ratio":0.0,"fill_cancel_interaction":0.0,"trader_type":"normal","predicted_trader_type":0},{"user_id":1038,"cancel_rate":0.0,"zero_fill_cancel_rate":0.0,"cancel_to_order_ratio":0.0,"avg_fill_ratio":1.0,"min_fill_ratio":1.0,"avg_time_to_cancel":-1773385.351703977,"min_time_to_cancel":-1773385.351703977,"std_time_to_cancel":0.0,"limit_order_ratio":0.0,"market_order_ratio":0.0,"self_trade_count":0,"both_sides_manip":0,"avg_engine_latency":1.5e-08,"max_engine_latency":1.5e-08,"unique_sides":1,"unique_instruments":1,"order_book_imbalance":1.0,"cancel_timing_regularity":0.0,"avg_price_deviation":0.0,"quote_to_trade_ratio":1.0,"latency_cancel_interaction":0.0,"cancel_intensity_ratio":0.0,"fill_cancel_interaction":0.0,"trader_type":"normal","predicted_trader_type":0},{"user_id":1104,"cancel_rate":0.0,"zero_fill_cancel_rate":0.0,"cancel_to_order_ratio":0.0,"avg_fill_ratio":1.0,"min_fill_ratio":1.0,"avg_time_to_cancel":-1773385.351698069,"min_time_to_cancel":-1773385.351698069,"std_time_to_cancel":0.0,"limit_order_ratio":0.0,"market_order_ratio":0.0,"self_trade_count":0,"both_sides_manip":0,"avg_engine_latency":1.7e-08,"max_engine_latency":1.7e-08,"unique_sides":1,"unique_instruments":1,"order_book_imbalance":1.0,"cancel_timing_regularity":0.0,"avg_price_deviation":0.004009844723769434,"quote_to_trade_ratio":1.0,"latency_cancel_interaction":0.0,"cancel_intensity_ratio":0.0,"fill_cancel_interaction":0.0,"trader_type":"normal","predicted_trader_type":0},{"user_id":1417,"cancel_rate":0.0,"zero_fill_cancel_rate":0.0,"cancel_to_order_ratio":0.0,"avg_fill_ratio":1.0,"min_fill_ratio":1.0,"avg_time_to_cancel":-1773385.3516992202,"min_time_to_cancel":-1773385.351699307,"std_time_to_cancel":7.787793489028383e-08,"limit_order_ratio":0.0,"market_order_ratio":0.0,"self_trade_count":0,"both_sides_manip":0,"avg_engine_latency":1.9e-08,"max_engine_latency":2.3e-08,"unique_sides":1,"unique_instruments":1,"order_book_imbalance":1.0,"cancel_timing_regularity":0.0,"avg_price_deviation":0.0008954859164112724,"quote_to_trade_ratio":1.0,"latency_cancel_interaction":0.0,"cancel_intensity_ratio":0.0,"fill_cancel_interaction":0.0,"trader_type":"normal","predicted_trader_type":0},{"user_id":1420,"cancel_rate":0.0,"zero_fill_cancel_rate":0.0,"cancel_to_order_ratio":0.0,"avg_fill_ratio":1.0,"min_fill_ratio":1.0,"avg_time_to_cancel":-1773385.351699361,"min_time_to_cancel":-1773385.351699361,"std_time_to_cancel":0.0,"limit_order_ratio":0.0,"market_order_ratio":0.0,"self_trade_count":0,"both_sides_manip":0,"avg_engine_latency":1.3e-08,"max_engine_latency":1.3e-08,"unique_sides":1,"unique_instruments":1,"order_book_imbalance":1.0,"cancel_timing_regularity":0.0,"avg_price_deviation":0.00011602731531918387,"quote_to_trade_ratio":1.0,"latency_cancel_interaction":0.0,"cancel_intensity_ratio":0.0,"fill_cancel_interaction":0.0,"trader_type":"normal","predicted_trader_type":0},{"user_id":1422,"cancel_rate":0.0,"zero_fill_cancel_rate":0.0,"cancel_to_order_ratio":0.0,"avg_fill_ratio":1.0,"min_fill_ratio":1.0,"avg_time_to_cancel":-1773385.3516996854,"min_time_to_cancel":-1773385.351699988,"std_time_to_cancel":4.2772465793477616e-07,"limit_order_ratio":0.0,"market_order_ratio":0.0,"self_trade_count":0,"both_sides_manip":0,"avg_engine_latency":1.7e-08,"max_engine_latency":1.9e-08,"unique_sides":1,"unique_instruments":1,"order_book_imbalance":1.0,"cancel_timing_regularity":0.0,"avg_price_deviation":0.00011602731531918387,"quote_to_trade_ratio":1.0,"latency_cancel_interaction":0.0,"cancel_intensity_ratio":0.0,"fill_cancel_interaction":0.0,"trader_type":"normal","predicted_trader_type":0},{"user_id":1429,"cancel_rate":0.0,"zero_fill_cancel_rate":0.0,"cancel_to_order_ratio":0.0,"avg_fill_ratio":1.0,"min_fill_ratio":1.0,"avg_time_to_cancel":-1773385.351697271,"min_time_to_cancel":-1773385.351697271,"std_time_to_cancel":0.0,"limit_order_ratio":0.0,"market_order_ratio":0.0,"self_trade_count":0,"both_sides_manip":0,"avg_engine_latency":6.16e-07,"max_engine_latency":6.16e-07,"unique_sides":1,"unique_instruments":1,"order_book_imbalance":1.0,"cancel_timing_regularity":0.0,"avg_price_deviation":0.002120267993053784,"quote_to_trade_ratio":1.0,"latency_cancel_interaction":0.0,"cancel_intensity_ratio":0.0,"fill_cancel_interaction":0.0,"trader_type":"normal","predicted_trader_type":0},{"user_id":1460,"cancel_rate":0.0,"zero_fill_cancel_rate":0.0,"cancel_to_order_ratio":0.0,"avg_fill_ratio":1.0,"min_fill_ratio":1.0,"avg_time_to_cancel":-1773385.3517031656,"min_time_to_cancel":-1773385.351703185,"std_time_to_cancel":2.7576428408721328e-08,"limit_order_ratio":0.0,"market_order_ratio":0.0,"self_trade_count":0,"both_sides_manip":0,"avg_engine_latency":1.95e-08,"max_engine_latency":2.4e-08,"unique_sides":1,"unique_instruments":1,"order_book_imbalance":1.0,"cancel_timing_regularity":0.0,"avg_price_deviation":0.00788288351791957,"quote_to_trade_ratio":1.0,"latency_cancel_interaction":0.0,"cancel_intensity_ratio":0.0,"fill_cancel_interaction":0.0,"trader_type":"normal","predicted_trader_type":0},{"user_id":1462,"cancel_rate":0.0,"zero_fill_cancel_rate":0.0,"cancel_to_order_ratio":0.0,"avg_fill_ratio":1.0,"min_fill_ratio":1.0,"avg_time_to_cancel":-1773385.351701338,"min_time_to_cancel":-1773385.351701352,"std_time_to_cancel":1.9756335239481578e-08,"limit_order_ratio":0.0,"market_order_ratio":0.0,"self_trade_count":0,"both_sides_manip":0,"avg_engine_latency":1.45e-08,"max_engine_latency":1.9e-08,"unique_sides":1,"unique_instruments":1,"order_book_imbalance":1.0,"cancel_timing_regularity":0.0,"avg_price_deviation":0.0023612681870305574,"quote_to_trade_ratio":1.0,"latency_cancel_interaction":0.0,"cancel_intensity_ratio":0.0,"fill_cancel_interaction":0.0,"trader_type":"normal","predicted_trader_type":0},{"user_id":1469,"cancel_rate":0.0,"zero_fill_cancel_rate":0.0,"cancel_to_order_ratio":0.0,"avg_fill_ratio":1.0,"min_fill_ratio":1.0,"avg_time_to_cancel":-1773385.351699123,"min_time_to_cancel":-1773385.351699123,"std_time_to_cancel":0.0,"limit_order_ratio":0.0,"market_order_ratio":0.0,"self_trade_count":0,"both_sides_manip":0,"avg_engine_latency":2.3e-08,"max_engine_latency":2.3e-08,"unique_sides":1,"unique_instruments":1,"order_book_imbalance":1.0,"cancel_timing_regularity":0.0,"avg_price_deviation":0.002120267993053784,"quote_to_trade_ratio":1.0,"latency_cancel_interaction":0.0,"cancel_intensity_ratio":0.0,"fill_cancel_interaction":0.0,"trader_type":"normal","predicted_trader_type":0},{"user_id":1500,"cancel_rate":0.0,"zero_fill_cancel_rate":0.0,"cancel_to_order_ratio":0.0,"avg_fill_ratio":1.0,"min_fill_ratio":1.0,"avg_time_to_cancel":-1773385.351700017,"min_time_to_cancel":-1773385.351700017,"std_time_to_cancel":0.0,"limit_order_ratio":0.0,"market_order_ratio":0.0,"self_trade_count":0,"both_sides_manip":0,"avg_engine_latency":1.4e-08,"max_engine_latency":1.4e-08,"unique_sides":1,"unique_instruments":1,"order_book_imbalance":1.0,"cancel_timing_regularity":0.0,"avg_price_deviation":0.0,"quote_to_trade_ratio":1.0,"latency_cancel_interaction":0.0,"cancel_intensity_ratio":0.0,"fill_cancel_interaction":0.0,"trader_type":"normal","predicted_trader_type":0},{"user_id":1514,"cancel_rate":0.0,"zero_fill_cancel_rate":0.0,"cancel_to_order_ratio":0.0,"avg_fill_ratio":1.0,"min_fill_ratio":1.0,"avg_time_to_cancel":-1773385.3517000584,"min_time_to_cancel":-1773385.351700075,"std_time_to_cancel":2.3378330033386533e-08,"limit_order_ratio":0.0,"market_order_ratio":0.0,"self_trade_count":0,"both_sides_manip":0,"avg_engine_latency":1.55e-08,"max_engine_latency":1.8e-08,"unique_sides":1,"unique_instruments":1,"order_book_imbalance":1.0,"cancel_timing_regularity":0.0,"avg_price_deviation":0.0026637790154018124,"quote_to_trade_ratio":1.0,"latency_cancel_interaction":0.0,"cancel_intensity_ratio":0.0,"fill_cancel_interaction":0.0,"trader_type":"normal","predicted_trader_type":0},{"user_id":1560,"cancel_rate":0.0,"zero_fill_cancel_rate":0.0,"cancel_to_order_ratio":0.0,"avg_fill_ratio":1.0,"min_fill_ratio":1.0,"avg_time_to_cancel":-1773385.351703069,"min_time_to_cancel":-1773385.351703069,"std_time_to_cancel":0.0,"limit_order_ratio":0.0,"market_order_ratio":0.0,"self_trade_count":0,"both_sides_manip":0,"avg_engine_latency":3.1e-08,"max_engine_latency":3.1e-08,"unique_sides":1,"unique_instruments":1,"order_book_imbalance":1.0,"cancel_timing_regularity":0.0,"avg_price_deviation":0.011891297594206525,"quote_to_trade_ratio":1.0,"latency_cancel_interaction":0.0,"cancel_intensity_ratio":0.0,"fill_cancel_interaction":0.0,"trader_type":"normal","predicted_trader_type":0},{"user_id":1565,"cancel_rate":0.0,"zero_fill_cancel_rate":0.0,"cancel_to_order_ratio":0.0,"avg_fill_ratio":1.0,"min_fill_ratio":1.0,"avg_time_to_cancel":-1773385.351700848,"min_time_to_cancel":-1773385.351700848,"std_time_to_cancel":0.0,"limit_order_ratio":0.0,"market_order_ratio":0.0,"self_trade_count":0,"both_sides_manip":0,"avg_engine_latency":1.61e-07,"max_engine_latency":1.61e-07,"unique_sides":1,"unique_instruments":1,"order_book_imbalance":1.0,"cancel_timing_regularity":0.0,"avg_price_deviation":0.016275075581664532,"quote_to_trade_ratio":1.0,"latency_cancel_interaction":0.0,"cancel_intensity_ratio":0.0,"fill_cancel_interaction":0.0,"trader_type":"normal","predicted_trader_type":0},{"user_id":1572,"cancel_rate":0.0,"zero_fill_cancel_rate":0.0,"cancel_to_order_ratio":0.0,"avg_fill_ratio":1.0,"min_fill_ratio":1.0,"avg_time_to_cancel":-1773385.351699337,"min_time_to_cancel":-1773385.351699337,"std_time_to_cancel":0.0,"limit_order_ratio":0.0,"market_order_ratio":0.0,"self_trade_count":0,"both_sides_manip":0,"avg_engine_latency":1.3e-08,"max_engine_latency":1.3e-08,"unique_sides":1,"unique_instruments":1,"order_book_imbalance":1.0,"cancel_timing_regularity":0.0,"avg_price_deviation":0.0006666411704244525,"quote_to_trade_ratio":1.0,"latency_cancel_interaction":0.0,"cancel_intensity_ratio":0.0,"fill_cancel_interaction":0.0,"trader_type":"normal","predicted_trader_type":0},{"user_id":1590,"cancel_rate":0.0,"zero_fill_cancel_rate":0.0,"cancel_to_order_ratio":0.0,"avg_fill_ratio":1.0,"min_fill_ratio":1.0,"avg_time_to_cancel":-1773385.351700221,"min_time_to_cancel":-1773385.351700221,"std_time_to_cancel":0.0,"limit_order_ratio":0.0,"market_order_ratio":0.0,"self_trade_count":0,"both_sides_manip":0,"avg_engine_latency":6.07e-07,"max_engine_latency":6.07e-07,"unique_sides":1,"unique_instruments":1,"order_book_imbalance":1.0,"cancel_timing_regularity":0.0,"avg_price_deviation":0.01608520140325726,"quote_to_trade_ratio":1.0,"latency_cancel_interaction":0.0,"cancel_intensity_ratio":0.0,"fill_cancel_interaction":0.0,"trader_type":"normal","predicted_trader_type":0},{"user_id":1617,"cancel_rate":0.0,"zero_fill_cancel_rate":0.0,"cancel_to_order_ratio":0.0,"avg_fill_ratio":1.0,"min_fill_ratio":1.0,"avg_time_to_cancel":-1773385.351701734,"min_time_to_cancel":-1773385.351701734,"std_time_to_cancel":0.0,"limit_order_ratio":0.0,"market_order_ratio":0.0,"self_trade_count":0,"both_sides_manip":0,"avg_engine_latency":1.5e-08,"max_engine_latency":1.5e-08,"unique_sides":1,"unique_instruments":1,"order_book_imbalance":1.0,"cancel_timing_regularity":0.0,"avg_price_deviation":0.0,"quote_to_trade_ratio":1.0,"latency_cancel_interaction":0.0,"cancel_intensity_ratio":0.0,"fill_cancel_interaction":0.0,"trader_type":"normal","predicted_trader_type":0},{"user_id":1618,"cancel_rate":0.0,"zero_fill_cancel_rate":0.0,"cancel_to_order_ratio":0.0,"avg_fill_ratio":0.6666666666666666,"min_fill_ratio":0.0,"avg_time_to_cancel":-1773385.351700824,"min_time_to_cancel":-1773385.351703142,"std_time_to_cancel":3.083946585681797e-06,"limit_order_ratio":0.3333333333333333,"market_order_ratio":0.0,"self_trade_count":0,"both_sides_manip":0,"avg_engine_latency":1.2999999999999999e-08,"max_engine_latency":2.3e-08,"unique_sides":1,"unique_instruments":1,"order_book_imbalance":1.0,"cancel_timing_regularity":0.0,"avg_price_deviation":0.0013360053440213844,"quote_to_trade_ratio":1.5,"latency_cancel_interaction":0.0,"cancel_intensity_ratio":0.0,"fill_cancel_interaction":0.0,"trader_type":"normal","predicted_trader_type":0},{"user_id":1620,"cancel_rate":0.0,"zero_fill_cancel_rate":0.0,"cancel_to_order_ratio":0.0,"avg_fill_ratio":1.0,"min_fill_ratio":1.0,"avg_time_to_cancel":-1773385.351698871,"min_time_to_cancel":-1773385.351698871,"std_time_to_cancel":0.0,"limit_order_ratio":0.0,"market_order_ratio":0.0,"self_trade_count":0,"both_sides_manip":0,"avg_engine_latency":2.2e-08,"max_engine_latency":2.2e-08,"unique_sides":1,"unique_instruments":1,"order_book_imbalance":1.0,"cancel_timing_regularity":0.0,"avg_price_deviation":0.0,"quote_to_trade_ratio":1.0,"latency_cancel_interaction":0.0,"cancel_intensity_ratio":0.0,"fill_cancel_interaction":0.0,"trader_type":"normal","predicted_trader_type":0},{"user_id":1624,"cancel_rate":0.0,"zero_fill_cancel_rate":0.0,"cancel_to_order_ratio":0.0,"avg_fill_ratio":1.0,"min_fill_ratio":1.0,"avg_time_to_cancel":-1773385.351701986,"min_time_to_cancel":-1773385.351701986,"std_time_to_cancel":0.0,"limit_order_ratio":0.0,"market_order_ratio":0.0,"self_trade_count":0,"both_sides_manip":0,"avg_engine_latency":1.3e-08,"max_engine_latency":1.3e-08,"unique_sides":1,"unique_instruments":1,"order_book_imbalance":1.0,"cancel_timing_regularity":0.0,"avg_price_deviation":0.0,"quote_to_trade_ratio":1.0,"latency_cancel_interaction":0.0,"cancel_intensity_ratio":0.0,"fill_cancel_interaction":0.0,"trader_type":"normal","predicted_trader_type":0},{"user_id":1625,"cancel_rate":0.0,"zero_fill_cancel_rate":0.0,"cancel_to_order_ratio":0.0,"avg_fill_ratio":1.0,"min_fill_ratio":1.0,"avg_time_to_cancel":-1773385.351701756,"min_time_to_cancel":-1773385.351701756,"std_time_to_cancel":0.0,"limit_order_ratio":0.0,"market_order_ratio":0.0,"self_trade_count":0,"both_sides_manip":0,"avg_engine_latency":2.21e-07,"max_engine_latency":2.21e-07,"unique_sides":1,"unique_instruments":1,"order_book_imbalance":1.0,"cancel_timing_regularity":0.0,"avg_price_deviation":0.0,"quote_to_trade_ratio":1.0,"latency_cancel_interaction":0.0,"cancel_intensity_ratio":0.0,"fill_cancel_interaction":0.0,"trader_type":"normal","predicted_trader_type":0},{"user_id":1632,"cancel_rate":0.0,"zero_fill_cancel_rate":0.0,"cancel_to_order_ratio":0.0,"avg_fill_ratio":1.0,"min_fill_ratio":1.0,"avg_time_to_cancel":-1773385.351698653,"min_time_to_cancel":-1773385.351698653,"std_time_to_cancel":0.0,"limit_order_ratio":0.0,"market_order_ratio":0.0,"self_trade_count":0,"both_sides_manip":0,"avg_engine_latency":1.9e-08,"max_engine_latency":1.9e-08,"unique_sides":1,"unique_instruments":1,"order_book_imbalance":1.0,"cancel_timing_regularity":0.0,"avg_price_deviation":0.002004008016032175,"quote_to_trade_ratio":1.0,"latency_cancel_interaction":0.0,"cancel_intensity_ratio":0.0,"fill_cancel_interaction":0.0,"trader_type":"normal","predicted_trader_type":0},{"user_id":1647,"cancel_rate":0.0,"zero_fill_cancel_rate":0.0,"cancel_to_order_ratio":0.0,"avg_fill_ratio":1.0,"min_fill_ratio":1.0,"avg_time_to_cancel":-1773385.351697333,"min_time_to_cancel":-1773385.351697333,"std_time_to_cancel":0.0,"limit_order_ratio":0.0,"market_order_ratio":0.0,"self_trade_count":0,"both_sides_manip":0,"avg_engine_latency":1.8e-08,"max_engine_latency":1.8e-08,"unique_sides":1,"unique_instruments":1,"order_book_imbalance":1.0,"cancel_timing_regularity":0.0,"avg_price_deviation":0.002004008016032175,"quote_to_trade_ratio":1.0,"latency_cancel_interaction":0.0,"cancel_intensity_ratio":0.0,"fill_cancel_interaction":0.0,"trader_type":"normal","predicted_trader_type":0},{"user_id":1672,"cancel_rate":0.0,"zero_fill_cancel_rate":0.0,"cancel_to_order_ratio":0.0,"avg_fill_ratio":1.0,"min_fill_ratio":1.0,"avg_time_to_cancel":-1773385.351701456,"min_time_to_cancel":-1773385.351701456,"std_time_to_cancel":0.0,"limit_order_ratio":0.0,"market_order_ratio":0.0,"self_trade_count":0,"both_sides_manip":0,"avg_engine_latency":1.7e-08,"max_engine_latency":1.7e-08,"unique_sides":1,"unique_instruments":1,"order_book_imbalance":1.0,"cancel_timing_regularity":0.0,"avg_price_deviation":0.002004008016032175,"quote_to_trade_ratio":1.0,"latency_cancel_interaction":0.0,"cancel_intensity_ratio":0.0,"fill_cancel_interaction":0.0,"trader_type":"normal","predicted_trader_type":0},{"user_id":1725,"cancel_rate":0.0,"zero_fill_cancel_rate":0.0,"cancel_to_order_ratio":0.0,"avg_fill_ratio":1.0,"min_fill_ratio":1.0,"avg_time_to_cancel":-1773385.351700278,"min_time_to_cancel":-1773385.351700278,"std_time_to_cancel":0.0,"limit_order_ratio":0.0,"market_order_ratio":0.0,"self_trade_count":0,"both_sides_manip":0,"avg_engine_latency":2.87e-07,"max_engine_latency":2.87e-07,"unique_sides":1,"unique_instruments":1,"order_book_imbalance":1.0,"cancel_timing_regularity":0.0,"avg_price_deviation":0.002004008016032175,"quote_to_trade_ratio":1.0,"latency_cancel_interaction":0.0,"cancel_intensity_ratio":0.0,"fill_cancel_interaction":0.0,"trader_type":"normal","predicted_trader_type":0},{"user_id":1729,"cancel_rate":0.0,"zero_fill_cancel_rate":0.0,"cancel_to_order_ratio":0.0,"avg_fill_ratio":1.0,"min_fill_ratio":1.0,"avg_time_to_cancel":-1773385.3517033735,"min_time_to_cancel":-1773385.35170357,"std_time_to_cancel":2.7790578236870754e-07,"limit_order_ratio":0.0,"market_order_ratio":0.0,"self_trade_count":0,"both_sides_manip":0,"avg_engine_latency":1.4e-08,"max_engine_latency":1.6e-08,"unique_sides":1,"unique_instruments":1,"order_book_imbalance":1.0,"cancel_timing_regularity":0.0,"avg_price_deviation":0.004723985629464783,"quote_to_trade_ratio":1.0,"latency_cancel_interaction":0.0,"cancel_intensity_ratio":0.0,"fill_cancel_interaction":0.0,"trader_type":"normal","predicted_trader_type":0},{"user_id":1751,"cancel_rate":0.0,"zero_fill_cancel_rate":0.0,"cancel_to_order_ratio":0.0,"avg_fill_ratio":1.0,"min_fill_ratio":1.0,"avg_time_to_cancel":-1773385.351697368,"min_time_to_cancel":-1773385.351697368,"std_time_to_cancel":0.0,"limit_order_ratio":0.0,"market_order_ratio":0.0,"self_trade_count":0,"both_sides_manip":0,"avg_engine_latency":2.2e-08,"max_engine_latency":2.2e-08,"unique_sides":1,"unique_instruments":1,"order_book_imbalance":1.0,"cancel_timing_regularity":0.0,"avg_price_deviation":0.002004008016032175,"quote_to_trade_ratio":1.0,"latency_cancel_interaction":0.0,"cancel_intensity_ratio":0.0,"fill_cancel_interaction":0.0,"trader_type":"normal","predicted_trader_type":0},{"user_id":1772,"cancel_rate":0.0,"zero_fill_cancel_rate":0.0,"cancel_to_order_ratio":0.0,"avg_fill_ratio":1.0,"min_fill_ratio":1.0,"avg_time_to_cancel":-1773385.351700836,"min_time_to_cancel":-1773385.351700836,"std_time_to_cancel":0.0,"limit_order_ratio":0.0,"market_order_ratio":0.0,"self_trade_count":0,"both_sides_manip":0,"avg_engine_latency":1.7e-08,"max_engine_latency":1.7e-08,"unique_sides":1,"unique_instruments":1,"order_book_imbalance":1.0,"cancel_timing_regularity":0.0,"avg_price_deviation":0.002004008016032175,"quote_to_trade_ratio":1.0,"latency_cancel_interaction":0.0,"cancel_intensity_ratio":0.0,"fill_cancel_interaction":0.0,"trader_type":"normal","predicted_trader_type":0},{"user_id":1819,"cancel_rate":0.0,"zero_fill_cancel_rate":0.0,"cancel_to_order_ratio":0.0,"avg_fill_ratio":1.0,"min_fill_ratio":1.0,"avg_time_to_cancel":-1773385.351697431,"min_time_to_cancel":-1773385.351697431,"std_time_to_cancel":0.0,"limit_order_ratio":0.0,"market_order_ratio":0.0,"self_trade_count":0,"both_sides_manip":0,"avg_engine_latency":1.6e-08,"max_engine_latency":1.6e-08,"unique_sides":1,"unique_instruments":1,"order_book_imbalance":1.0,"cancel_timing_regularity":0.0,"avg_price_deviation":0.003343731094228144,"quote_to_trade_ratio":1.0,"latency_cancel_interaction":0.0,"cancel_intensity_ratio":0.0,"fill_cancel_interaction":0.0,"trader_type":"normal","predicted_trader_type":0},{"user_id":1883,"cancel_rate":0.0,"zero_fill_cancel_rate":0.0,"cancel_to_order_ratio":0.0,"avg_fill_ratio":1.0,"min_fill_ratio":1.0,"avg_time_to_cancel":-1773385.351697501,"min_time_to_cancel":-1773385.351697501,"std_time_to_cancel":0.0,"limit_order_ratio":0.0,"market_order_ratio":0.0,"self_trade_count":0,"both_sides_manip":0,"avg_engine_latency":3.9e-07,"max_engine_latency":3.9e-07,"unique_sides":1,"unique_instruments":1,"order_book_imbalance":1.0,"cancel_timing_regularity":0.0,"avg_price_deviation":0.0007045242071874135,"quote_to_trade_ratio":1.0,"latency_cancel_interaction":0.0,"cancel_intensity_ratio":0.0,"fill_cancel_interaction":0.0,"trader_type":"normal","predicted_trader_type":0},{"user_id":1892,"cancel_rate":0.0,"zero_fill_cancel_rate":0.0,"cancel_to_order_ratio":0.0,"avg_fill_ratio":1.0,"min_fill_ratio":1.0,"avg_time_to_cancel":-1773385.351697976,"min_time_to_cancel":-1773385.351697976,"std_time_to_cancel":0.0,"limit_order_ratio":0.0,"market_order_ratio":0.0,"self_trade_count":0,"both_sides_manip":0,"avg_engine_latency":1.6e-08,"max_engine_latency":1.6e-08,"unique_sides":1,"unique_instruments":1,"order_book_imbalance":1.0,"cancel_timing_regularity":0.0,"avg_price_deviation":0.0007045242071874135,"quote_to_trade_ratio":1.0,"latency_cancel_interaction":0.0,"cancel_intensity_ratio":0.0,"fill_cancel_interaction":0.0,"trader_type":"normal","predicted_trader_type":0},{"user_id":1916,"cancel_rate":0.0,"zero_fill_cancel_rate":0.0,"cancel_to_order_ratio":0.0,"avg_fill_ratio":1.0,"min_fill_ratio":1.0,"avg_time_to_cancel":-1773385.35169746,"min_time_to_cancel":-1773385.35169746,"std_time_to_cancel":0.0,"limit_order_ratio":0.0,"market_order_ratio":0.0,"self_trade_count":0,"both_sides_manip":0,"avg_engine_latency":3e-08,"max_engine_latency":3e-08,"unique_sides":1,"unique_instruments":1,"order_book_imbalance":1.0,"cancel_timing_regularity":0.0,"avg_price_deviation":0.001969489207671962,"quote_to_trade_ratio":1.0,"latency_cancel_interaction":0.0,"cancel_intensity_ratio":0.0,"fill_cancel_interaction":0.0,"trader_type":"normal","predicted_trader_type":0},{"user_id":1983,"cancel_rate":0.0,"zero_fill_cancel_rate":0.0,"cancel_to_order_ratio":0.0,"avg_fill_ratio":1.0,"min_fill_ratio":1.0,"avg_time_to_cancel":-1773385.351698274,"min_time_to_cancel":-1773385.351698274,"std_time_to_cancel":0.0,"limit_order_ratio":0.0,"market_order_ratio":0.0,"self_trade_count":0,"both_sides_manip":0,"avg_engine_latency":1.81e-07,"max_engine_latency":1.81e-07,"unique_sides":1,"unique_instruments":1,"order_book_imbalance":1.0,"cancel_timing_regularity":0.0,"avg_price_deviation":0.0,"quote_to_trade_ratio":1.0,"latency_cancel_interaction":0.0,"cancel_intensity_ratio":0.0,"fill_cancel_interaction":0.0,"trader_type":"normal","predicted_trader_type":0},{"user_id":2178,"cancel_rate":0.0,"zero_fill_cancel_rate":0.0,"cancel_to_order_ratio":0.0,"avg_fill_ratio":1.0,"min_fill_ratio":1.0,"avg_time_to_cancel":-1773385.351697621,"min_time_to_cancel":-1773385.351697621,"std_time_to_cancel":0.0,"limit_order_ratio":0.0,"market_order_ratio":0.0,"self_trade_count":0,"both_sides_manip":0,"avg_engine_latency":1.8e-08,"max_engine_latency":1.8e-08,"unique_sides":1,"unique_instruments":1,"order_book_imbalance":1.0,"cancel_timing_regularity":0.0,"avg_price_deviation":0.003692717865931378,"quote_to_trade_ratio":1.0,"latency_cancel_interaction":0.0,"cancel_intensity_ratio":0.0,"fill_cancel_interaction":0.0,"trader_type":"normal","predicted_trader_type":0},{"user_id":2247,"cancel_rate":0.0,"zero_fill_cancel_rate":0.0,"cancel_to_order_ratio":0.0,"avg_fill_ratio":1.0,"min_fill_ratio":1.0,"avg_time_to_cancel":-1773385.351697508,"min_time_to_cancel":-1773385.351697508,"std_time_to_cancel":0.0,"limit_order_ratio":0.0,"market_order_ratio":0.0,"self_trade_count":0,"both_sides_manip":0,"avg_engine_latency":2.4e-08,"max_engine_latency":2.4e-08,"unique_sides":1,"unique_instruments":1,"order_book_imbalance":1.0,"cancel_timing_regularity":0.0,"avg_price_deviation":0.0033174516203507876,"quote_to_trade_ratio":1.0,"latency_cancel_interaction":0.0,"cancel_intensity_ratio":0.0,"fill_cancel_interaction":0.0,"trader_type":"normal","predicted_trader_type":0},{"user_id":2303,"cancel_rate":0.0,"zero_fill_cancel_rate":0.0,"cancel_to_order_ratio":0.0,"avg_fill_ratio":1.0,"min_fill_ratio":1.0,"avg_time_to_cancel":-1773385.351697563,"min_time_to_cancel":-1773385.351697563,"std_time_to_cancel":0.0,"limit_order_ratio":0.0,"market_order_ratio":0.0,"self_trade_count":0,"both_sides_manip":0,"avg_engine_latency":1.9e-08,"max_engine_latency":1.9e-08,"unique_sides":1,"unique_instruments":1,"order_book_imbalance":1.0,"cancel_timing_regularity":0.0,"avg_price_deviation":0.00025560969233290505,"quote_to_trade_ratio":1.0,"latency_cancel_interaction":0.0,"cancel_intensity_ratio":0.0,"fill_cancel_interaction":0.0,"trader_type":"normal","predicted_trader_type":0},{"user_id":2342,"cancel_rate":0.0,"zero_fill_cancel_rate":0.0,"cancel_to_order_ratio":0.0,"avg_fill_ratio":1.0,"min_fill_ratio":1.0,"avg_time_to_cancel":-1773385.351697541,"min_time_to_cancel":-1773385.351697541,"std_time_to_cancel":0.0,"limit_order_ratio":0.0,"market_order_ratio":0.0,"self_trade_count":0,"both_sides_manip":0,"avg_engine_latency":1.3e-08,"max_engine_latency":1.3e-08,"unique_sides":1,"unique_instruments":1,"order_book_imbalance":1.0,"cancel_timing_regularity":0.0,"avg_price_deviation":0.0,"quote_to_trade_ratio":1.0,"latency_cancel_interaction":0.0,"cancel_intensity_ratio":0.0,"fill_cancel_interaction":0.0,"trader_type":"normal","predicted_trader_type":0},{"user_id":2528,"cancel_rate":0.0,"zero_fill_cancel_rate":0.0,"cancel_to_order_ratio":0.0,"avg_fill_ratio":1.0,"min_fill_ratio":1.0,"avg_time_to_cancel":-1773385.351698148,"min_time_to_cancel":-1773385.351698148,"std_time_to_cancel":0.0,"limit_order_ratio":0.0,"market_order_ratio":0.0,"self_trade_count":0,"both_sides_manip":0,"avg_engine_latency":5.725e-06,"max_engine_latency":5.725e-06,"unique_sides":1,"unique_instruments":1,"order_book_imbalance":1.0,"cancel_timing_regularity":0.0,"avg_price_deviation":0.0,"quote_to_trade_ratio":1.0,"latency_cancel_interaction":0.0,"cancel_intensity_ratio":0.0,"fill_cancel_interaction":0.0,"trader_type":"normal","predicted_trader_type":0},{"user_id":2616,"cancel_rate":0.0,"zero_fill_cancel_rate":0.0,"cancel_to_order_ratio":0.0,"avg_fill_ratio":1.0,"min_fill_ratio":1.0,"avg_time_to_cancel":-1773385.35170363,"min_time_to_cancel":-1773385.35170363,"std_time_to_cancel":0.0,"limit_order_ratio":0.0,"market_order_ratio":0.0,"self_trade_count":0,"both_sides_manip":0,"avg_engine_latency":1.88e-07,"max_engine_latency":1.88e-07,"unique_sides":1,"unique_instruments":1,"order_book_imbalance":1.0,"cancel_timing_regularity":0.0,"avg_price_deviation":0.0009990010003052359,"quote_to_trade_ratio":1.0,"latency_cancel_interaction":0.0,"cancel_intensity_ratio":0.0,"fill_cancel_interaction":0.0,"trader_type":"normal","predicted_trader_type":0},{"user_id":2624,"cancel_rate":0.0,"zero_fill_cancel_rate":0.0,"cancel_to_order_ratio":0.0,"avg_fill_ratio":1.0,"min_fill_ratio":1.0,"avg_time_to_cancel":-1773385.3517006426,"min_time_to_cancel":-1773385.351703573,"std_time_to_cancel":4.144467542108238e-06,"limit_order_ratio":0.0,"market_order_ratio":0.0,"self_trade_count":0,"both_sides_manip":0,"avg_engine_latency":2.8999999999999998e-08,"max_engine_latency":4.4e-08,"unique_sides":1,"unique_instruments":1,"order_book_imbalance":1.0,"cancel_timing_regularity":0.0,"avg_price_deviation":0.0009990010003052359,"quote_to_trade_ratio":1.0,"latency_cancel_interaction":0.0,"cancel_intensity_ratio":0.0,"fill_cancel_interaction":0.0,"trader_type":"normal","predicted_trader_type":0},{"user_id":2625,"cancel_rate":0.0,"zero_fill_cancel_rate":0.0,"cancel_to_order_ratio":0.0,"avg_fill_ratio":1.0,"min_fill_ratio":1.0,"avg_time_to_cancel":-1773385.351697689,"min_time_to_cancel":-1773385.351697689,"std_time_to_cancel":0.0,"limit_order_ratio":0.0,"market_order_ratio":0.0,"self_trade_count":0,"both_sides_manip":0,"avg_engine_latency":1.4e-08,"max_engine_latency":1.4e-08,"unique_sides":1,"unique_instruments":1,"order_book_imbalance":1.0,"cancel_timing_regularity":0.0,"avg_price_deviation":0.0009990010003052359,"quote_to_trade_ratio":1.0,"latency_cancel_interaction":0.0,"cancel_intensity_ratio":0.0,"fill_cancel_interaction":0.0,"trader_type":"normal","predicted_trader_type":0},{"user_id":2635,"cancel_rate":0.0,"zero_fill_cancel_rate":0.0,"cancel_to_order_ratio":0.0,"avg_fill_ratio":1.0,"min_fill_ratio":1.0,"avg_time_to_cancel":-1773385.35169762,"min_time_to_cancel":-1773385.35169762,"std_time_to_cancel":0.0,"limit_order_ratio":0.0,"market_order_ratio":0.0,"self_trade_count":0,"both_sides_manip":0,"avg_engine_latency":3.3e-08,"max_engine_latency":3.3e-08,"unique_sides":1,"unique_instruments":1,"order_book_imbalance":1.0,"cancel_timing_regularity":0.0,"avg_price_deviation":0.004006014026310758,"quote_to_trade_ratio":1.0,"latency_cancel_interaction":0.0,"cancel_intensity_ratio":0.0,"fill_cancel_interaction":0.0,"trader_type":"normal","predicted_trader_type":0},{"user_id":2662,"cancel_rate":0.0,"zero_fill_cancel_rate":0.0,"cancel_to_order_ratio":0.0,"avg_fill_ratio":1.0,"min_fill_ratio":1.0,"avg_time_to_cancel":-1773385.351697663,"min_time_to_cancel":-1773385.351697663,"std_time_to_cancel":0.0,"limit_order_ratio":0.0,"market_order_ratio":0.0,"self_trade_count":0,"both_sides_manip":0,"avg_engine_latency":1.3e-08,"max_engine_latency":1.3e-08,"unique_sides":1,"unique_instruments":1,"order_book_imbalance":1.0,"cancel_timing_regularity":0.0,"avg_price_deviation":0.004006014026310758,"quote_to_trade_ratio":1.0,"latency_cancel_interaction":0.0,"cancel_intensity_ratio":0.0,"fill_cancel_interaction":0.0,"trader_type":"normal","predicted_trader_type":0},{"user_id":2816,"cancel_rate":0.0,"zero_fill_cancel_rate":0.0,"cancel_to_order_ratio":0.0,"avg_fill_ratio":0.3333333333333333,"min_fill_ratio":0.0,"avg_time_to_cancel":-1773385.3516997618,"min_time_to_cancel":-1773385.351699767,"std_time_to_cancel":9.107220552679126e-09,"limit_order_ratio":1.0,"market_order_ratio":0.0,"self_trade_count":0,"both_sides_manip":1,"avg_engine_latency":1.4333333333333334e-08,"max_engine_latency":3.4e-08,"unique_sides":2,"unique_instruments":1,"order_book_imbalance":0.3333333333333333,"cancel_timing_regularity":0.0,"avg_price_deviation":0.003328010645655226,"quote_to_trade_ratio":3.0,"latency_cancel_interaction":0.0,"cancel_intensity_ratio":0.0,"fill_cancel_interaction":0.0,"trader_type":"normal","predicted_trader_type":0},{"user_id":2817,"cancel_rate":0.0,"zero_fill_cancel_rate":0.0,"cancel_to_order_ratio":0.0,"avg_fill_ratio":0.0,"min_fill_ratio":0.0,"avg_time_to_cancel":-1773385.351702351,"min_time_to_cancel":-1773385.351702351,"std_time_to_cancel":0.0,"limit_order_ratio":1.0,"market_order_ratio":0.0,"self_trade_count":0,"both_sides_manip":0,"avg_engine_latency":4e-09,"max_engine_latency":4e-09,"unique_sides":1,"unique_instruments":1,"order_book_imbalance":1.0,"cancel_timing_regularity":0.0,"avg_price_deviation":0.0020371637852911314,"quote_to_trade_ratio":0.0,"latency_cancel_interaction":0.0,"cancel_intensity_ratio":0.0,"fill_cancel_interaction":0.0,"trader_type":"normal","predicted_trader_type":1},{"user_id":2818,"cancel_rate":0.0,"zero_fill_cancel_rate":0.0,"cancel_to_order_ratio":0.0,"avg_fill_ratio":0.5652173913043479,"min_fill_ratio":0.0,"avg_time_to_cancel":-1773385.351698789,"min_time_to_cancel":-1773385.351699075,"std_time_to_cancel":1.600499420287046e-07,"limit_order_ratio":0.8,"market_order_ratio":0.0,"self_trade_count":0,"both_sides_manip":1,"avg_engine_latency":5.784e-07,"max_engine_latency":2.499e-06,"unique_sides":2,"unique_instruments":1,"order_book_imbalance":0.2,"cancel_timing_regularity":0.0,"avg_price_deviation":0.0023952095766113695,"quote_to_trade_ratio":1.6666666666666667,"latency_cancel_interaction":0.0,"cancel_intensity_ratio":0.0,"fill_cancel_interaction":0.0,"trader_type":"normal","predicted_trader_type":0},{"user_id":2819,"cancel_rate":0.0,"zero_fill_cancel_rate":0.0,"cancel_to_order_ratio":0.0,"avg_fill_ratio":0.75,"min_fill_ratio":0.0,"avg_time_to_cancel":-1773385.3516998317,"min_time_to_cancel":-1773385.351699859,"std_time_to_cancel":3.4259877435516304e-08,"limit_order_ratio":0.5,"market_order_ratio":0.0,"self_trade_count":0,"both_sides_manip":1,"avg_engine_latency":3.61e-07,"max_engine_latency":1.402e-06,"unique_sides":2,"unique_instruments":1,"order_book_imbalance":0.0,"cancel_timing_regularity":0.0,"avg_price_deviation":0.0020175838878886557,"quote_to_trade_ratio":1.3333333333333333,"latency_cancel_interaction":0.0,"cancel_intensity_ratio":0.0,"fill_cancel_interaction":0.0,"trader_type":"normal","predicted_trader_type":0},{"user_id":2820,"cancel_rate":0.0,"zero_fill_cancel_rate":0.0,"cancel_to_order_ratio":0.0,"avg_fill_ratio":0.75,"min_fill_ratio":0.0,"avg_time_to_cancel":-1773385.351700969,"min_time_to_cancel":-1773385.351702141,"std_time_to_cancel":8.199555603293505e-07,"limit_order_ratio":0.5,"market_order_ratio":0.0,"self_trade_count":0,"both_sides_manip":1,"avg_engine_latency":2.475e-07,"max_engine_latency":5.31e-07,"unique_sides":2,"unique_instruments":1,"order_book_imbalance":0.5,"cancel_timing_regularity":0.0,"avg_price_deviation":0.002008330029655947,"quote_to_trade_ratio":1.3333333333333333,"latency_cancel_interaction":0.0,"cancel_intensity_ratio":0.0,"fill_cancel_interaction":0.0,"trader_type":"normal","predicted_trader_type":0},{"user_id":2821,"cancel_rate":0.0,"zero_fill_cancel_rate":0.0,"cancel_to_order_ratio":0.0,"avg_fill_ratio":0.3333333333333333,"min_fill_ratio":0.0,"avg_time_to_cancel":-1773385.3517011118,"min_time_to_cancel":-1773385.351701116,"std_time_to_cancel":6.8556665742469285e-09,"limit_order_ratio":1.0,"market_order_ratio":0.0,"self_trade_count":0,"both_sides_manip":1,"avg_engine_latency":4.4e-08,"max_engine_latency":1.26e-07,"unique_sides":2,"unique_instruments":1,"order_book_imbalance":0.3333333333333333,"cancel_timing_regularity":0.0,"avg_price_deviation":0.0013306719870063164,"quote_to_trade_ratio":3.0,"latency_cancel_interaction":0.0,"cancel_intensity_ratio":0.0,"fill_cancel_interaction":0.0,"trader_type":"normal","predicted_trader_type":0},{"user_id":2822,"cancel_rate":0.0,"zero_fill_cancel_rate":0.0,"cancel_to_order_ratio":0.0,"avg_fill_ratio":0.5,"min_fill_ratio":0.0,"avg_time_to_cancel":-1773385.3517018547,"min_time_to_cancel":-1773385.351702123,"std_time_to_cancel":1.7988614665909526e-07,"limit_order_ratio":0.75,"market_order_ratio":0.0,"self_trade_count":0,"both_sides_manip":1,"avg_engine_latency":9.825e-08,"max_engine_latency":3.75e-07,"unique_sides":2,"unique_instruments":1,"order_book_imbalance":0.0,"cancel_timing_regularity":0.0,"avg_price_deviation":0.001035126622475112,"quote_to_trade_ratio":2.0,"latency_cancel_interaction":0.0,"cancel_intensity_ratio":0.0,"fill_cancel_interaction":0.0,"trader_type":"normal","predicted_trader_type":0},{"user_id":2823,"cancel_rate":0.0,"zero_fill_cancel_rate":0.0,"cancel_to_order_ratio":0.0,"avg_fill_ratio":0.6666666666666666,"min_fill_ratio":0.0,"avg_time_to_cancel":-1773385.3517019225,"min_time_to_cancel":-1773385.351703847,"std_time_to_cancel":1.666851148196485e-06,"limit_order_ratio":0.6666666666666666,"market_order_ratio":0.0,"self_trade_count":0,"both_sides_manip":0,"avg_engine_latency":2.3566666666666665e-07,"max_engine_latency":6.79e-07,"unique_sides":1,"unique_instruments":1,"order_book_imbalance":1.0,"cancel_timing_regularity":0.0,"avg_price_deviation":0.002012437379371403,"quote_to_trade_ratio":1.5,"latency_cancel_interaction":0.0,"cancel_intensity_ratio":0.0,"fill_cancel_interaction":0.0,"trader_type":"normal","predicted_trader_type":0},{"user_id":2825,"cancel_rate":0.0,"zero_fill_cancel_rate":0.0,"cancel_to_order_ratio":0.0,"avg_fill_ratio":0.7133333333333333,"min_fill_ratio":0.0,"avg_time_to_cancel":-1773385.3517016773,"min_time_to_cancel":-1773385.35170381,"std_time_to_cancel":1.3289465291672623e-06,"limit_order_ratio":0.6,"market_order_ratio":0.0,"self_trade_count":0,"both_sides_manip":0,"avg_engine_latency":2.3060000000000001e-07,"max_engine_latency":6.14e-07,"unique_sides":1,"unique_instruments":1,"order_book_imbalance":1.0,"cancel_timing_regularity":0.0,"avg_price_deviation":0.002007492098187457,"quote_to_trade_ratio":1.25,"latency_cancel_interaction":0.0,"cancel_intensity_ratio":0.0,"fill_cancel_interaction":0.0,"trader_type":"normal","predicted_trader_type":0},{"user_id":2848,"cancel_rate":0.0,"zero_fill_cancel_rate":0.0,"cancel_to_order_ratio":0.0,"avg_fill_ratio":1.0,"min_fill_ratio":1.0,"avg_time_to_cancel":-1773385.351702101,"min_time_to_cancel":-1773385.351702101,"std_time_to_cancel":0.0,"limit_order_ratio":0.0,"market_order_ratio":0.0,"self_trade_count":0,"both_sides_manip":0,"avg_engine_latency":1.4e-08,"max_engine_latency":1.4e-08,"unique_sides":1,"unique_instruments":1,"order_book_imbalance":1.0,"cancel_timing_regularity":0.0,"avg_price_deviation":0.003037200873497006,"quote_to_trade_ratio":1.0,"latency_cancel_interaction":0.0,"cancel_intensity_ratio":0.0,"fill_cancel_interaction":0.0,"trader_type":"normal","predicted_trader_type":0},{"user_id":2864,"cancel_rate":0.0,"zero_fill_cancel_rate":0.0,"cancel_to_order_ratio":0.0,"avg_fill_ratio":1.0,"min_fill_ratio":1.0,"avg_time_to_cancel":-1773385.3517016824,"min_time_to_cancel":-1773385.351702075,"std_time_to_cancel":3.480383582126522e-07,"limit_order_ratio":0.0,"market_order_ratio":0.0,"self_trade_count":0,"both_sides_manip":1,"avg_engine_latency":8.2e-08,"max_engine_latency":1.39e-07,"unique_sides":2,"unique_instruments":1,"order_book_imbalance":0.3333333333333333,"cancel_timing_regularity":0.0,"avg_price_deviation":0.002370509481359756,"quote_to_trade_ratio":1.0,"latency_cancel_interaction":0.0,"cancel_intensity_ratio":0.0,"fill_cancel_interaction":0.0,"trader_type":"normal","predicted_trader_type":0},{"user_id":2971,"cancel_rate":0.0,"zero_fill_cancel_rate":0.0,"cancel_to_order_ratio":0.0,"avg_fill_ratio":1.0,"min_fill_ratio":1.0,"avg_time_to_cancel":-1773385.35169904,"min_time_to_cancel":-1773385.35169904,"std_time_to_cancel":0.0,"limit_order_ratio":0.0,"market_order_ratio":0.0,"self_trade_count":0,"both_sides_manip":0,"avg_engine_latency":2.3e-08,"max_engine_latency":2.3e-08,"unique_sides":1,"unique_instruments":1,"order_book_imbalance":1.0,"cancel_timing_regularity":0.0,"avg_price_deviation":0.002446129551493081,"quote_to_trade_ratio":1.0,"latency_cancel_interaction":0.0,"cancel_intensity_ratio":0.0,"fill_cancel_interaction":0.0,"trader_type":"normal","predicted_trader_type":0},{"user_id":2985,"cancel_rate":0.0,"zero_fill_cancel_rate":0.0,"cancel_to_order_ratio":0.0,"avg_fill_ratio":1.0,"min_fill_ratio":1.0,"avg_time_to_cancel":-1773385.351697786,"min_time_to_cancel":-1773385.351697786,"std_time_to_cancel":0.0,"limit_order_ratio":0.0,"market_order_ratio":0.0,"self_trade_count":0,"both_sides_manip":0,"avg_engine_latency":1.5e-08,"max_engine_latency":1.5e-08,"unique_sides":1,"unique_instruments":1,"order_book_imbalance":1.0,"cancel_timing_regularity":0.0,"avg_price_deviation":0.0019960079805095795,"quote_to_trade_ratio":1.0,"latency_cancel_interaction":0.0,"cancel_intensity_ratio":0.0,"fill_cancel_interaction":0.0,"trader_type":"normal","predicted_trader_type":0},{"user_id":3015,"cancel_rate":0.0,"zero_fill_cancel_rate":0.0,"cancel_to_order_ratio":0.0,"avg_fill_ratio":1.0,"min_fill_ratio":1.0,"avg_time_to_cancel":-1773385.3517012459,"min_time_to_cancel":-1773385.351701297,"std_time_to_cancel":3.992376858231685e-08,"limit_order_ratio":0.0,"market_order_ratio":0.0,"self_trade_count":0,"both_sides_manip":0,"avg_engine_latency":1.9666666666666667e-08,"max_engine_latency":4.8e-08,"unique_sides":1,"unique_instruments":1,"order_book_imbalance":1.0,"cancel_timing_regularity":0.0,"avg_price_deviation":0.0011973841717535644,"quote_to_trade_ratio":1.0,"latency_cancel_interaction":0.0,"cancel_intensity_ratio":0.0,"fill_cancel_interaction":0.0,"trader_type":"normal","predicted_trader_type":0}]}